{
"meta":{"test_sets":[],"test_metrics":[],"learn_metrics":[{"best_value":"Min","name":"RMSE"}],"launch_mode":"Train","parameters":"","iteration_count":1000,"learn_sets":["learn"],"name":"experiment"},
"iterations":[
{"learn":[14.61268541],"iteration":0,"passed_time":0.04775225653,"remaining_time":47.70450427},
{"learn":[14.23196558],"iteration":1,"passed_time":0.04822377696,"remaining_time":24.0636647},
{"learn":[13.86674177],"iteration":2,"passed_time":0.04930826064,"remaining_time":16.38677862},
{"learn":[13.49946468],"iteration":3,"passed_time":0.05031573096,"remaining_time":12.52861701},
{"learn":[13.16661202],"iteration":4,"passed_time":0.05139143375,"remaining_time":10.22689532},
{"learn":[12.85632158],"iteration":5,"passed_time":0.05234203413,"remaining_time":8.67133032},
{"learn":[12.56784336],"iteration":6,"passed_time":0.0535024988,"remaining_time":7.589711615},
{"learn":[12.31617801],"iteration":7,"passed_time":0.05447597459,"remaining_time":6.755020849},
{"learn":[12.01509946],"iteration":8,"passed_time":0.05529642452,"remaining_time":6.088750744},
{"learn":[11.71512571],"iteration":9,"passed_time":0.05614764515,"remaining_time":5.55861687},
{"learn":[11.43264457],"iteration":10,"passed_time":0.05728808381,"remaining_time":5.150719535},
{"learn":[11.17973129],"iteration":11,"passed_time":0.05803318277,"remaining_time":4.778065382},
{"learn":[10.93746433],"iteration":12,"passed_time":0.0589375233,"remaining_time":4.474718115},
{"learn":[10.69387075],"iteration":13,"passed_time":0.05976371213,"remaining_time":4.209072869},
{"learn":[10.4615922],"iteration":14,"passed_time":0.06060882158,"remaining_time":3.979979284},
{"learn":[10.2299235],"iteration":15,"passed_time":0.06147172333,"remaining_time":3.780510985},
{"learn":[10.01419731],"iteration":16,"passed_time":0.06236153333,"remaining_time":3.605963957},
{"learn":[9.795856918],"iteration":17,"passed_time":0.06349511409,"remaining_time":3.464011224},
{"learn":[9.60040151],"iteration":18,"passed_time":0.0639767764,"remaining_time":3.303221981},
{"learn":[9.418664989],"iteration":19,"passed_time":0.06490940477,"remaining_time":3.180560834},
{"learn":[9.249278645],"iteration":20,"passed_time":0.06572136806,"remaining_time":3.063867587},
{"learn":[9.090113396],"iteration":21,"passed_time":0.06651340987,"remaining_time":2.956823403},
{"learn":[8.909548708],"iteration":22,"passed_time":0.06732239848,"remaining_time":2.859738405},
{"learn":[8.740140208],"iteration":23,"passed_time":0.06819502972,"remaining_time":2.773264542},
{"learn":[8.59377682],"iteration":24,"passed_time":0.06915932012,"remaining_time":2.697213485},
{"learn":[8.453885414],"iteration":25,"passed_time":0.07015716046,"remaining_time":2.628195165},
{"learn":[8.317732234],"iteration":26,"passed_time":0.07117930377,"remaining_time":2.565091206},
{"learn":[8.180896085],"iteration":27,"passed_time":0.07208524798,"remaining_time":2.502387894},
{"learn":[8.053220863],"iteration":28,"passed_time":0.072508926,"remaining_time":2.427798867},
{"learn":[7.924234474],"iteration":29,"passed_time":0.07288354381,"remaining_time":2.356567916},
{"learn":[7.818879511],"iteration":30,"passed_time":0.07324468207,"remaining_time":2.289486998},
{"learn":[7.719346395],"iteration":31,"passed_time":0.07363101823,"remaining_time":2.227338301},
{"learn":[7.624163594],"iteration":32,"passed_time":0.07399367641,"remaining_time":2.168238942},
{"learn":[7.524952543],"iteration":33,"passed_time":0.07436054856,"remaining_time":2.112714409},
{"learn":[7.424464745],"iteration":34,"passed_time":0.07471946029,"remaining_time":2.060122262},
{"learn":[7.327482321],"iteration":35,"passed_time":0.07507199951,"remaining_time":2.01026132},
{"learn":[7.238666841],"iteration":36,"passed_time":0.07543194217,"remaining_time":1.963269198},
{"learn":[7.158842395],"iteration":37,"passed_time":0.07579158772,"remaining_time":1.918723879},
{"learn":[7.074348246],"iteration":38,"passed_time":0.07614604635,"remaining_time":1.876316681},
{"learn":[6.992269093],"iteration":39,"passed_time":0.07650550576,"remaining_time":1.836132138},
{"learn":[6.925219745],"iteration":40,"passed_time":0.07686243937,"remaining_time":1.797831204},
{"learn":[6.86013671],"iteration":41,"passed_time":0.07724407114,"remaining_time":1.76190048},
{"learn":[6.786739622],"iteration":42,"passed_time":0.07760184024,"remaining_time":1.727092119},
{"learn":[6.73057926],"iteration":43,"passed_time":0.07795064302,"remaining_time":1.69365488},
{"learn":[6.666356486],"iteration":44,"passed_time":0.0783102585,"remaining_time":1.661917708},
{"learn":[6.606182832],"iteration":45,"passed_time":0.07867299329,"remaining_time":1.63160947},
{"learn":[6.547854615],"iteration":46,"passed_time":0.07902891386,"remaining_time":1.602437338},
{"learn":[6.49240675],"iteration":47,"passed_time":0.07938859735,"remaining_time":1.574540514},
{"learn":[6.431317261],"iteration":48,"passed_time":0.07974315192,"remaining_time":1.547668112},
{"learn":[6.377586395],"iteration":49,"passed_time":0.08010279031,"remaining_time":1.521953016},
{"learn":[6.327558015],"iteration":50,"passed_time":0.08045686162,"remaining_time":1.49712866},
{"learn":[6.282040317],"iteration":51,"passed_time":0.08122111101,"remaining_time":1.480723332},
{"learn":[6.237655841],"iteration":52,"passed_time":0.08158019241,"remaining_time":1.457668721},
{"learn":[6.192792003],"iteration":53,"passed_time":0.08194789576,"remaining_time":1.435605729},
{"learn":[6.150579347],"iteration":54,"passed_time":0.0823133382,"remaining_time":1.414292811},
{"learn":[6.115693845],"iteration":55,"passed_time":0.0826687304,"remaining_time":1.393558598},
{"learn":[6.078780782],"iteration":56,"passed_time":0.08302589883,"remaining_time":1.373568818},
{"learn":[6.045146957],"iteration":57,"passed_time":0.08338193466,"remaining_time":1.354237628},
{"learn":[6.008080327],"iteration":58,"passed_time":0.08375740013,"remaining_time":1.335859551},
{"learn":[5.977575734],"iteration":59,"passed_time":0.08411546705,"remaining_time":1.317808984},
{"learn":[5.948036502],"iteration":60,"passed_time":0.08449316694,"remaining_time":1.300640717},
{"learn":[5.914888282],"iteration":61,"passed_time":0.08505070213,"remaining_time":1.286734816},
{"learn":[5.884957796],"iteration":62,"passed_time":0.08541560475,"remaining_time":1.270387645},
{"learn":[5.849539885],"iteration":63,"passed_time":0.0857667787,"remaining_time":1.254339138},
{"learn":[5.821387627],"iteration":64,"passed_time":0.08613218749,"remaining_time":1.238978389},
{"learn":[5.797012279],"iteration":65,"passed_time":0.08650013425,"remaining_time":1.22410796},
{"learn":[5.768685095],"iteration":66,"passed_time":0.08685331137,"remaining_time":1.209464769},
{"learn":[5.755484587],"iteration":67,"passed_time":0.08702819172,"remaining_time":1.192798157},
{"learn":[5.731887055],"iteration":68,"passed_time":0.08738318229,"remaining_time":1.179039749},
{"learn":[5.707148487],"iteration":69,"passed_time":0.08774360391,"remaining_time":1.165736452},
{"learn":[5.685365039],"iteration":70,"passed_time":0.08829135913,"remaining_time":1.15524891},
{"learn":[5.663541834],"iteration":71,"passed_time":0.08864527723,"remaining_time":1.142539129},
{"learn":[5.638108797],"iteration":72,"passed_time":0.08900159514,"remaining_time":1.130198338},
{"learn":[5.619204893],"iteration":73,"passed_time":0.089357084,"remaining_time":1.118171078},
{"learn":[5.598472793],"iteration":74,"passed_time":0.08971224424,"remaining_time":1.106451012},
{"learn":[5.577007075],"iteration":75,"passed_time":0.090062902,"remaining_time":1.094975282},
{"learn":[5.562637084],"iteration":76,"passed_time":0.09041652085,"remaining_time":1.08382401},
{"learn":[5.54729991],"iteration":77,"passed_time":0.09080214966,"remaining_time":1.073327974},
{"learn":[5.530737623],"iteration":78,"passed_time":0.09115794852,"remaining_time":1.062740134},
{"learn":[5.513704873],"iteration":79,"passed_time":0.09153267729,"remaining_time":1.052625789},
{"learn":[5.501575529],"iteration":80,"passed_time":0.09188644792,"remaining_time":1.042514144},
{"learn":[5.484080734],"iteration":81,"passed_time":0.09223424625,"remaining_time":1.032573635},
{"learn":[5.472178894],"iteration":82,"passed_time":0.09258794313,"remaining_time":1.022929444},
{"learn":[5.458923342],"iteration":83,"passed_time":0.09293348556,"remaining_time":1.013417533},
{"learn":[5.451382371],"iteration":84,"passed_time":0.09316125456,"remaining_time":1.002853505},
{"learn":[5.441410748],"iteration":85,"passed_time":0.09353710807,"remaining_time":0.9941036834},
{"learn":[5.434047468],"iteration":86,"passed_time":0.09376559872,"remaining_time":0.9839999038},
{"learn":[5.422107497],"iteration":87,"passed_time":0.09412235836,"remaining_time":0.9754498957},
{"learn":[5.40731265],"iteration":88,"passed_time":0.09447601443,"remaining_time":0.9670522376},
{"learn":[5.396360181],"iteration":89,"passed_time":0.09483309409,"remaining_time":0.9588679513},
{"learn":[5.383793239],"iteration":90,"passed_time":0.09520661222,"remaining_time":0.9510198957},
{"learn":[5.369605034],"iteration":91,"passed_time":0.09555753631,"remaining_time":0.9431113366},
{"learn":[5.357467333],"iteration":92,"passed_time":0.0959134583,"remaining_time":0.9354140503},
{"learn":[5.341109968],"iteration":93,"passed_time":0.09626948769,"remaining_time":0.9278739983},
{"learn":[5.330529276],"iteration":94,"passed_time":0.09662173195,"remaining_time":0.9204491307},
{"learn":[5.319862075],"iteration":95,"passed_time":0.09697616338,"remaining_time":0.9131922051},
{"learn":[5.313052243],"iteration":96,"passed_time":0.09732644527,"remaining_time":0.9060389699},
{"learn":[5.299677207],"iteration":97,"passed_time":0.09768131413,"remaining_time":0.8990667893},
{"learn":[5.287546698],"iteration":98,"passed_time":0.0980351993,"remaining_time":0.8922193391},
{"learn":[5.279803754],"iteration":99,"passed_time":0.09838266759,"remaining_time":0.8854440083},
{"learn":[5.272254612],"iteration":100,"passed_time":0.09875488775,"remaining_time":0.8790162781},
{"learn":[5.268813888],"iteration":101,"passed_time":0.09892640394,"remaining_time":0.8709403013},
{"learn":[5.258113767],"iteration":102,"passed_time":0.09928562064,"remaining_time":0.8646524439},
{"learn":[5.251018576],"iteration":103,"passed_time":0.09964359092,"remaining_time":0.8584678602},
{"learn":[5.24171237],"iteration":104,"passed_time":0.09999728207,"remaining_time":0.8523577853},
{"learn":[5.233984943],"iteration":105,"passed_time":0.1003503375,"remaining_time":0.8463509595},
{"learn":[5.226240449],"iteration":106,"passed_time":0.1007041733,"remaining_time":0.8404563245},
{"learn":[5.220541644],"iteration":107,"passed_time":0.101052079,"remaining_time":0.834615319},
{"learn":[5.211712096],"iteration":108,"passed_time":0.1014100528,"remaining_time":0.8289574043},
{"learn":[5.203388597],"iteration":109,"passed_time":0.1017671153,"remaining_time":0.8233884783},
{"learn":[5.196026544],"iteration":110,"passed_time":0.1021191885,"remaining_time":0.8178735003},
{"learn":[5.188716772],"iteration":111,"passed_time":0.10249262,"remaining_time":0.8126200583},
{"learn":[5.182163132],"iteration":112,"passed_time":0.1028397403,"remaining_time":0.8072464571},
{"learn":[5.17764747],"iteration":113,"passed_time":0.1031997044,"remaining_time":0.8020608609},
{"learn":[5.170548056],"iteration":114,"passed_time":0.103547744,"remaining_time":0.7968674216},
{"learn":[5.165901827],"iteration":115,"passed_time":0.1038261916,"remaining_time":0.7912271844},
{"learn":[5.160333668],"iteration":116,"passed_time":0.1041778202,"remaining_time":0.7862308993},
{"learn":[5.148953243],"iteration":117,"passed_time":0.1045340966,"remaining_time":0.7813480777},
{"learn":[5.144729126],"iteration":118,"passed_time":0.1048137419,"remaining_time":0.7759740051},
{"learn":[5.139939946],"iteration":119,"passed_time":0.1051668596,"remaining_time":0.7712236369},
{"learn":[5.132898872],"iteration":120,"passed_time":0.1055194246,"remaining_time":0.7665419356},
{"learn":[5.129073077],"iteration":121,"passed_time":0.1059233855,"remaining_time":0.7623010859},
{"learn":[5.127123916],"iteration":122,"passed_time":0.1060959312,"remaining_time":0.7564726152},
{"learn":[5.121282057],"iteration":123,"passed_time":0.106456355,"remaining_time":0.7520626368},
{"learn":[5.114489821],"iteration":124,"passed_time":0.1068119584,"remaining_time":0.7476837087},
{"learn":[5.107777291],"iteration":125,"passed_time":0.1071598355,"remaining_time":0.7433150492},
{"learn":[5.103518754],"iteration":126,"passed_time":0.1075119688,"remaining_time":0.7390389664},
{"learn":[5.101133351],"iteration":127,"passed_time":0.1077317222,"remaining_time":0.7339223575},
{"learn":[5.096462705],"iteration":128,"passed_time":0.1081249091,"remaining_time":0.7300526808},
{"learn":[5.08562082],"iteration":129,"passed_time":0.1084917361,"remaining_time":0.7260600804},
{"learn":[5.080483682],"iteration":130,"passed_time":0.1088458118,"remaining_time":0.7220382474},
{"learn":[5.07437499],"iteration":131,"passed_time":0.1091963793,"remaining_time":0.7180489185},
{"learn":[5.070683732],"iteration":132,"passed_time":0.1095588342,"remaining_time":0.7141917987},
{"learn":[5.06432037],"iteration":133,"passed_time":0.1099138505,"remaining_time":0.7103387652},
{"learn":[5.057436484],"iteration":134,"passed_time":0.1102627027,"remaining_time":0.706498058},
{"learn":[5.053254656],"iteration":135,"passed_time":0.1106160896,"remaining_time":0.7027375103},
{"learn":[5.04801663],"iteration":136,"passed_time":0.1109724569,"remaining_time":0.6990454766},
{"learn":[5.045680836],"iteration":137,"passed_time":0.1112482126,"remaining_time":0.6948982552},
{"learn":[5.041857933],"iteration":138,"passed_time":0.1116332758,"remaining_time":0.6914838162},
{"learn":[5.035264888],"iteration":139,"passed_time":0.1119852845,"remaining_time":0.6879096048},
{"learn":[5.028771948],"iteration":140,"passed_time":0.1123396035,"remaining_time":0.6843951733},
{"learn":[5.024912247],"iteration":141,"passed_time":0.1126821204,"remaining_time":0.680853939},
{"learn":[5.02239068],"iteration":142,"passed_time":0.1130569373,"remaining_time":0.6775510157},
{"learn":[5.017110572],"iteration":143,"passed_time":0.1134727354,"remaining_time":0.6745323716},
{"learn":[5.010707886],"iteration":144,"passed_time":0.1138556795,"remaining_time":0.6713559032},
{"learn":[5.004389868],"iteration":145,"passed_time":0.1142302457,"remaining_time":0.6681686977},
{"learn":[4.997628683],"iteration":146,"passed_time":0.1145880692,"remaining_time":0.6649226059},
{"learn":[4.991497851],"iteration":147,"passed_time":0.1149634782,"remaining_time":0.6618167797},
{"learn":[4.988345253],"iteration":148,"passed_time":0.1152555592,"remaining_time":0.6582716837},
{"learn":[4.98460423],"iteration":149,"passed_time":0.1156773046,"remaining_time":0.6555047258},
{"learn":[4.982441783],"iteration":150,"passed_time":0.1159721176,"remaining_time":0.6520551512},
{"learn":[4.977461771],"iteration":151,"passed_time":0.1164036533,"remaining_time":0.6494098553},
{"learn":[4.973601586],"iteration":152,"passed_time":0.116703906,"remaining_time":0.6460667213},
{"learn":[4.968328804],"iteration":153,"passed_time":0.1171262685,"remaining_time":0.6434339164},
{"learn":[4.9640736],"iteration":154,"passed_time":0.1174191592,"remaining_time":0.6401238035},
{"learn":[4.960865882],"iteration":155,"passed_time":0.1178393388,"remaining_time":0.6375410384},
{"learn":[4.957014156],"iteration":156,"passed_time":0.1181254369,"remaining_time":0.6342658807},
{"learn":[4.952244852],"iteration":157,"passed_time":0.1185404625,"remaining_time":0.6317156292},
{"learn":[4.949695675],"iteration":158,"passed_time":0.118824397,"remaining_time":0.6284988544},
{"learn":[4.946584698],"iteration":159,"passed_time":0.1192445687,"remaining_time":0.6260339857},
{"learn":[4.940192834],"iteration":160,"passed_time":0.1195285425,"remaining_time":0.6228847652},
{"learn":[4.936727994],"iteration":161,"passed_time":0.1199288272,"remaining_time":0.6203725752},
{"learn":[4.932342063],"iteration":162,"passed_time":0.1202243375,"remaining_time":0.6173482853},
{"learn":[4.925830838],"iteration":163,"passed_time":0.120671356,"remaining_time":0.615129595},
{"learn":[4.922571773],"iteration":164,"passed_time":0.1209601537,"remaining_time":0.6121316871},
{"learn":[4.918395814],"iteration":165,"passed_time":0.1213396306,"remaining_time":0.6096219993},
{"learn":[4.911142452],"iteration":166,"passed_time":0.1216360122,"remaining_time":0.6067233423},
{"learn":[4.908276131],"iteration":167,"passed_time":0.1220648209,"remaining_time":0.6045114941},
{"learn":[4.904584645],"iteration":168,"passed_time":0.1223549246,"remaining_time":0.6016387119},
{"learn":[4.89795517],"iteration":169,"passed_time":0.1227598434,"remaining_time":0.5993568825},
{"learn":[4.895556491],"iteration":170,"passed_time":0.1230573226,"remaining_time":0.5965761427},
{"learn":[4.890591233],"iteration":171,"passed_time":0.1234878066,"remaining_time":0.5944645573},
{"learn":[4.884629277],"iteration":172,"passed_time":0.1237799964,"remaining_time":0.5917113125},
{"learn":[4.880550786],"iteration":173,"passed_time":0.1241927318,"remaining_time":0.5895586005},
{"learn":[4.876384842],"iteration":174,"passed_time":0.1244899361,"remaining_time":0.5868811271},
{"learn":[4.872638238],"iteration":175,"passed_time":0.1249439527,"remaining_time":0.5849648695},
{"learn":[4.869137118],"iteration":176,"passed_time":0.1252294078,"remaining_time":0.5822813707},
{"learn":[4.863587157],"iteration":177,"passed_time":0.1256023195,"remaining_time":0.5800286891},
{"learn":[4.858028614],"iteration":178,"passed_time":0.1258980332,"remaining_time":0.5774429345},
{"learn":[4.853838176],"iteration":179,"passed_time":0.1263330698,"remaining_time":0.5755173181},
{"learn":[4.853462329],"iteration":180,"passed_time":0.1264591473,"remaining_time":0.572210175},
{"learn":[4.851573196],"iteration":181,"passed_time":0.1267415297,"remaining_time":0.5696405015},
{"learn":[4.848442087],"iteration":182,"passed_time":0.1271726938,"remaining_time":0.5677600593},
{"learn":[4.845547104],"iteration":183,"passed_time":0.1274617357,"remaining_time":0.5652650889},
{"learn":[4.839868817],"iteration":184,"passed_time":0.1279011517,"remaining_time":0.563456425},
{"learn":[4.836336958],"iteration":185,"passed_time":0.1281901134,"remaining_time":0.5610040448},
{"learn":[4.831124789],"iteration":186,"passed_time":0.1286209289,"remaining_time":0.5591915251},
{"learn":[4.827407333],"iteration":187,"passed_time":0.1289136994,"remaining_time":0.5567974676},
{"learn":[4.824088918],"iteration":188,"passed_time":0.1293044063,"remaining_time":0.5548458916},
{"learn":[4.820934539],"iteration":189,"passed_time":0.1295898263,"remaining_time":0.5524618912},
{"learn":[4.816975227],"iteration":190,"passed_time":0.1300195221,"remaining_time":0.5507109601},
{"learn":[4.812340486],"iteration":191,"passed_time":0.1303113669,"remaining_time":0.5483936689},
{"learn":[4.806402747],"iteration":192,"passed_time":0.1306851757,"remaining_time":0.5464400869},
{"learn":[4.801521788],"iteration":193,"passed_time":0.1309740128,"remaining_time":0.5441497647},
{"learn":[4.797601172],"iteration":194,"passed_time":0.1314099164,"remaining_time":0.5424870909},
{"learn":[4.792694629],"iteration":195,"passed_time":0.1317055306,"remaining_time":0.5402614622},
{"learn":[4.789794613],"iteration":196,"passed_time":0.1321041929,"remaining_time":0.5384754666},
{"learn":[4.785367055],"iteration":197,"passed_time":0.1323882312,"remaining_time":0.5362391991},
{"learn":[4.780376856],"iteration":198,"passed_time":0.1328240024,"remaining_time":0.5346332959},
{"learn":[4.776691261],"iteration":199,"passed_time":0.133146708,"remaining_time":0.5325868322},
{"learn":[4.773470753],"iteration":200,"passed_time":0.1338664924,"remaining_time":0.5321359574},
{"learn":[4.77207327],"iteration":201,"passed_time":0.1341717738,"remaining_time":0.5300449281},
{"learn":[4.767347177],"iteration":202,"passed_time":0.1345966864,"remaining_time":0.5284411777},
{"learn":[4.763983068],"iteration":203,"passed_time":0.1349179058,"remaining_time":0.5264443777},
{"learn":[4.761588849],"iteration":204,"passed_time":0.135345796,"remaining_time":0.5248775992},
{"learn":[4.758558086],"iteration":205,"passed_time":0.135630377,"remaining_time":0.5227695113},
{"learn":[4.753678804],"iteration":206,"passed_time":0.1360376011,"remaining_time":0.5211488777},
{"learn":[4.746510889],"iteration":207,"passed_time":0.1363283849,"remaining_time":0.5190965425},
{"learn":[4.744840601],"iteration":208,"passed_time":0.1367632576,"remaining_time":0.5176063959},
{"learn":[4.741702222],"iteration":209,"passed_time":0.1370519666,"remaining_time":0.5155764457},
{"learn":[4.739352853],"iteration":210,"passed_time":0.1374311384,"remaining_time":0.5139012711},
{"learn":[4.735539287],"iteration":211,"passed_time":0.1377251467,"remaining_time":0.5119217718},
{"learn":[4.730726751],"iteration":212,"passed_time":0.13815095,"remaining_time":0.5104450594},
{"learn":[4.726416092],"iteration":213,"passed_time":0.1384381964,"remaining_time":0.5084692632},
{"learn":[4.721293082],"iteration":214,"passed_time":0.1388635192,"remaining_time":0.5070133144},
{"learn":[4.718443695],"iteration":215,"passed_time":0.139153736,"remaining_time":0.5050765232},
{"learn":[4.711627962],"iteration":216,"passed_time":0.139589999,"remaining_time":0.5036818857},
{"learn":[4.709790764],"iteration":217,"passed_time":0.1398698304,"remaining_time":0.5017348964},
{"learn":[4.706913073],"iteration":218,"passed_time":0.1402390981,"remaining_time":0.5001220804},
{"learn":[4.703846389],"iteration":219,"passed_time":0.1405355499,"remaining_time":0.4982624042},
{"learn":[4.701001135],"iteration":220,"passed_time":0.140970293,"remaining_time":0.4969043359},
{"learn":[4.700380864],"iteration":221,"passed_time":0.1412567468,"remaining_time":0.4950349055},
{"learn":[4.695837486],"iteration":222,"passed_time":0.1416272824,"remaining_time":0.4934726386},
{"learn":[4.691242996],"iteration":223,"passed_time":0.14192658,"remaining_time":0.4916742235},
{"learn":[4.690284609],"iteration":224,"passed_time":0.142279286,"remaining_time":0.4900730963},
{"learn":[4.68827119],"iteration":225,"passed_time":0.1427213445,"remaining_time":0.4887890293},
{"learn":[4.686922425],"iteration":226,"passed_time":0.1430133439,"remaining_time":0.487001387},
{"learn":[4.686085874],"iteration":227,"passed_time":0.1433868656,"remaining_time":0.4855028959},
{"learn":[4.683230741],"iteration":228,"passed_time":0.1436703784,"remaining_time":0.4837111867},
{"learn":[4.6773487],"iteration":229,"passed_time":0.144091395,"remaining_time":0.4823929309},
{"learn":[4.671462906],"iteration":230,"passed_time":0.1443770727,"remaining_time":0.4806319001},
{"learn":[4.664799601],"iteration":231,"passed_time":0.1448065873,"remaining_time":0.4793597374},
{"learn":[4.660979386],"iteration":232,"passed_time":0.1450986018,"remaining_time":0.4776421785},
{"learn":[4.656281279],"iteration":233,"passed_time":0.1455094801,"remaining_time":0.4763259048},
{"learn":[4.651997094],"iteration":234,"passed_time":0.1458117645,"remaining_time":0.4746638292},
{"learn":[4.650151977],"iteration":235,"passed_time":0.1462365712,"remaining_time":0.473409917},
{"learn":[4.648478046],"iteration":236,"passed_time":0.1465221122,"remaining_time":0.4717146483},
{"learn":[4.646364602],"iteration":237,"passed_time":0.1468994928,"remaining_time":0.4703252669},
{"learn":[4.642635873],"iteration":238,"passed_time":0.1471901656,"remaining_time":0.4686682679},
{"learn":[4.640860821],"iteration":239,"passed_time":0.1476120091,"remaining_time":0.4674380287},
{"learn":[4.639446822],"iteration":240,"passed_time":0.1478907072,"remaining_time":0.4657636796},
{"learn":[4.637120072],"iteration":241,"passed_time":0.1482590621,"remaining_time":0.4643816903},
{"learn":[4.633769267],"iteration":242,"passed_time":0.148549878,"remaining_time":0.4627664925},
{"learn":[4.630491517],"iteration":243,"passed_time":0.14898601,"remaining_time":0.4616123918},
{"learn":[4.627813333],"iteration":244,"passed_time":0.1492746696,"remaining_time":0.4600096962},
{"learn":[4.622496304],"iteration":245,"passed_time":0.1496919591,"remaining_time":0.4588119395},
{"learn":[4.618979301],"iteration":246,"passed_time":0.1499836034,"remaining_time":0.4572374629},
{"learn":[4.616563458],"iteration":247,"passed_time":0.1504144139,"remaining_time":0.4560953194},
{"learn":[4.614759385],"iteration":248,"passed_time":0.1506956493,"remaining_time":0.4545077614},
{"learn":[4.61251363],"iteration":249,"passed_time":0.1510650021,"remaining_time":0.4531950063},
{"learn":[4.608796693],"iteration":250,"passed_time":0.15135913,"remaining_time":0.4516652923},
{"learn":[4.60847774],"iteration":251,"passed_time":0.1517897966,"remaining_time":0.450550666},
{"learn":[4.605195659],"iteration":252,"passed_time":0.1520751278,"remaining_time":0.4490123339},
{"learn":[4.60103766],"iteration":253,"passed_time":0.1524474546,"remaining_time":0.4477393747},
{"learn":[4.599325598],"iteration":254,"passed_time":0.1527333765,"remaining_time":0.4462210412},
{"learn":[4.597012808],"iteration":255,"passed_time":0.153180982,"remaining_time":0.445182229},
{"learn":[4.594161533],"iteration":256,"passed_time":0.1535098447,"remaining_time":0.4438047261},
{"learn":[4.592197259],"iteration":257,"passed_time":0.1539006869,"remaining_time":0.4426136035},
{"learn":[4.58952828],"iteration":258,"passed_time":0.1541909073,"remaining_time":0.441140781},
{"learn":[4.585816572],"iteration":259,"passed_time":0.1546182526,"remaining_time":0.4400673344},
{"learn":[4.582934052],"iteration":260,"passed_time":0.1549052427,"remaining_time":0.4386014343},
{"learn":[4.582234842],"iteration":261,"passed_time":0.1552820763,"remaining_time":0.4373976042},
{"learn":[4.57571562],"iteration":262,"passed_time":0.1555755283,"remaining_time":0.4359664045},
{"learn":[4.571197349],"iteration":263,"passed_time":0.1560107124,"remaining_time":0.4349389559},
{"learn":[4.56723703],"iteration":264,"passed_time":0.1562965491,"remaining_time":0.4335017495},
{"learn":[4.560335567],"iteration":265,"passed_time":0.1567070021,"remaining_time":0.432417066},
{"learn":[4.554709345],"iteration":266,"passed_time":0.1570029585,"remaining_time":0.4310231033},
{"learn":[4.552806306],"iteration":267,"passed_time":0.1574431477,"remaining_time":0.4300312839},
{"learn":[4.550766241],"iteration":268,"passed_time":0.1577272375,"remaining_time":0.4286193703},
{"learn":[4.549216045],"iteration":269,"passed_time":0.1580679352,"remaining_time":0.4273688619},
{"learn":[4.547687452],"iteration":270,"passed_time":0.1584575403,"remaining_time":0.4262566306},
{"learn":[4.545642435],"iteration":271,"passed_time":0.1587472502,"remaining_time":0.4248823461},
{"learn":[4.543930359],"iteration":272,"passed_time":0.1591603564,"remaining_time":0.4238446121},
{"learn":[4.541029943],"iteration":273,"passed_time":0.1594506892,"remaining_time":0.4224861326},
{"learn":[4.537781449],"iteration":274,"passed_time":0.159867307,"remaining_time":0.4214683549},
{"learn":[4.53066128],"iteration":275,"passed_time":0.1601604612,"remaining_time":0.420131065},
{"learn":[4.526763956],"iteration":276,"passed_time":0.1605463399,"remaining_time":0.4190433349},
{"learn":[4.522036004],"iteration":277,"passed_time":0.1609014243,"remaining_time":0.4178806774},
{"learn":[4.515307629],"iteration":278,"passed_time":0.1612896397,"remaining_time":0.4168094275},
{"learn":[4.51109143],"iteration":279,"passed_time":0.1615920545,"remaining_time":0.4155224259},
{"learn":[4.508233494],"iteration":280,"passed_time":0.1620208103,"remaining_time":0.4145657032},
{"learn":[4.502555629],"iteration":281,"passed_time":0.1623175406,"remaining_time":0.4132765749},
{"learn":[4.500081355],"iteration":282,"passed_time":0.1626425473,"remaining_time":0.4120661003},
{"learn":[4.495281743],"iteration":283,"passed_time":0.1630831674,"remaining_time":0.4111533376},
{"learn":[4.492138869],"iteration":284,"passed_time":0.1633686898,"remaining_time":0.4098547832},
{"learn":[4.491708261],"iteration":285,"passed_time":0.1637360194,"remaining_time":0.4087675451},
{"learn":[4.489398865],"iteration":286,"passed_time":0.1640417454,"remaining_time":0.4075322804},
{"learn":[4.485796373],"iteration":287,"passed_time":0.1644788475,"remaining_time":0.4066282618},
{"learn":[4.479542205],"iteration":288,"passed_time":0.1647723389,"remaining_time":0.4053741625},
{"learn":[4.475986993],"iteration":289,"passed_time":0.1651509752,"remaining_time":0.4043351462},
{"learn":[4.468661855],"iteration":290,"passed_time":0.1654468528,"remaining_time":0.4030990332},
{"learn":[4.463785664],"iteration":291,"passed_time":0.1658846157,"remaining_time":0.4022133833},
{"learn":[4.460445831],"iteration":292,"passed_time":0.1661731221,"remaining_time":0.4009706394},
{"learn":[4.45692492],"iteration":293,"passed_time":0.1665479619,"remaining_time":0.3999417043},
{"learn":[4.454031688],"iteration":294,"passed_time":0.1668390492,"remaining_time":0.3987170497},
{"learn":[4.451672391],"iteration":295,"passed_time":0.1672728329,"remaining_time":0.3978380891},
{"learn":[4.45031553],"iteration":296,"passed_time":0.1675769774,"remaining_time":0.3966552697},
{"learn":[4.446782666],"iteration":297,"passed_time":0.1679807257,"remaining_time":0.3957129847},
{"learn":[4.444369689],"iteration":298,"passed_time":0.1682702781,"remaining_time":0.3945065716},
{"learn":[4.44411683],"iteration":299,"passed_time":0.1686944755,"remaining_time":0.3936204428},
{"learn":[4.440876943],"iteration":300,"passed_time":0.168983977,"remaining_time":0.3924245845},
{"learn":[4.439336453],"iteration":301,"passed_time":0.1693613963,"remaining_time":0.3914379291},
{"learn":[4.436666901],"iteration":302,"passed_time":0.1696598047,"remaining_time":0.3902735442},
{"learn":[4.433043336],"iteration":303,"passed_time":0.1700974444,"remaining_time":0.3894336228},
{"learn":[4.431419305],"iteration":304,"passed_time":0.170388869,"remaining_time":0.3882631604},
{"learn":[4.428859646],"iteration":305,"passed_time":0.1707721853,"remaining_time":0.3873068517},
{"learn":[4.424552441],"iteration":306,"passed_time":0.1721086042,"remaining_time":0.3885057418},
{"learn":[4.422706391],"iteration":307,"passed_time":0.1725507171,"remaining_time":0.3876788839},
{"learn":[4.421427994],"iteration":308,"passed_time":0.1729710013,"remaining_time":0.3868057019},
{"learn":[4.418733158],"iteration":309,"passed_time":0.1734070982,"remaining_time":0.3859706379},
{"learn":[4.415656941],"iteration":310,"passed_time":0.1738429338,"remaining_time":0.3851375607},
{"learn":[4.410747417],"iteration":311,"passed_time":0.1742856,"remaining_time":0.3843220924},
{"learn":[4.408126521],"iteration":312,"passed_time":0.1747169969,"remaining_time":0.3834842711},
{"learn":[4.407843853],"iteration":313,"passed_time":0.1750878288,"remaining_time":0.3825167216},
{"learn":[4.405219398],"iteration":314,"passed_time":0.1754416553,"remaining_time":0.3815159806},
{"learn":[4.402708465],"iteration":315,"passed_time":0.1757967318,"remaining_time":0.3805220397},
{"learn":[4.40104971],"iteration":316,"passed_time":0.1761551918,"remaining_time":0.3795394195},
{"learn":[4.400830038],"iteration":317,"passed_time":0.1765005588,"remaining_time":0.3785326449},
{"learn":[4.39784288],"iteration":318,"passed_time":0.1768540323,"remaining_time":0.3775473229},
{"learn":[4.393741845],"iteration":319,"passed_time":0.1772109093,"remaining_time":0.3765731824},
{"learn":[4.393425936],"iteration":320,"passed_time":0.1775623303,"remaining_time":0.3755913466},
{"learn":[4.390505974],"iteration":321,"passed_time":0.177917744,"remaining_time":0.3746218336},
{"learn":[4.390305136],"iteration":322,"passed_time":0.1782663778,"remaining_time":0.3736419126},
{"learn":[4.38568203],"iteration":323,"passed_time":0.1786370537,"remaining_time":0.3727118774},
{"learn":[4.383057135],"iteration":324,"passed_time":0.1789923056,"remaining_time":0.37175325},
{"learn":[4.380662684],"iteration":325,"passed_time":0.1793451727,"remaining_time":0.3707933938},
{"learn":[4.37805727],"iteration":326,"passed_time":0.1796960731,"remaining_time":0.3698332025},
{"learn":[4.373708319],"iteration":327,"passed_time":0.1800494479,"remaining_time":0.3688817956},
{"learn":[4.36887921],"iteration":328,"passed_time":0.1803987912,"remaining_time":0.3679258021},
{"learn":[4.367895929],"iteration":329,"passed_time":0.1807487724,"remaining_time":0.3669747803},
{"learn":[4.362140573],"iteration":330,"passed_time":0.1811119825,"remaining_time":0.3660541279},
{"learn":[4.361931924],"iteration":331,"passed_time":0.1814818852,"remaining_time":0.3651502992},
{"learn":[4.359656377],"iteration":332,"passed_time":0.1818332582,"remaining_time":0.3642125622},
{"learn":[4.354281355],"iteration":333,"passed_time":0.1821990908,"remaining_time":0.3633071691},
{"learn":[4.348589447],"iteration":334,"passed_time":0.1826921586,"remaining_time":0.3626575686},
{"learn":[4.346355698],"iteration":335,"passed_time":0.1833470425,"remaining_time":0.3623286791},
{"learn":[4.343894047],"iteration":336,"passed_time":0.1837887372,"remaining_time":0.3615784355},
{"learn":[4.341561356],"iteration":337,"passed_time":0.1842246602,"remaining_time":0.3608187131},
{"learn":[4.338869061],"iteration":338,"passed_time":0.1845795297,"remaining_time":0.3599028589},
{"learn":[4.333720063],"iteration":339,"passed_time":0.1849310044,"remaining_time":0.3589837144},
{"learn":[4.330892223],"iteration":340,"passed_time":0.1852810529,"remaining_time":0.3580651432},
{"learn":[4.328311474],"iteration":341,"passed_time":0.1856882813,"remaining_time":0.3572599097},
{"learn":[4.324580133],"iteration":342,"passed_time":0.1860703806,"remaining_time":0.3564088631},
{"learn":[4.323354432],"iteration":343,"passed_time":0.186456081,"remaining_time":0.3555674103},
{"learn":[4.323159553],"iteration":344,"passed_time":0.1868404727,"remaining_time":0.3547261148},
{"learn":[4.318639682],"iteration":345,"passed_time":0.1872379931,"remaining_time":0.353912276},
{"learn":[4.312712208],"iteration":346,"passed_time":0.1876237465,"remaining_time":0.353078693},
{"learn":[4.311461062],"iteration":347,"passed_time":0.188015435,"remaining_time":0.3522588034},
{"learn":[4.311178356],"iteration":348,"passed_time":0.188360235,"remaining_time":0.3513539053},
{"learn":[4.311102505],"iteration":349,"passed_time":0.1886986281,"remaining_time":0.3504403094},
{"learn":[4.310232308],"iteration":350,"passed_time":0.1890659463,"remaining_time":0.3495834734},
{"learn":[4.305128197],"iteration":351,"passed_time":0.1893814411,"remaining_time":0.3486340166},
{"learn":[4.304595496],"iteration":352,"passed_time":0.1898040062,"remaining_time":0.3478843967},
{"learn":[4.3004992],"iteration":353,"passed_time":0.1900936796,"remaining_time":0.3468941159},
{"learn":[4.297581524],"iteration":354,"passed_time":0.1905214603,"remaining_time":0.3461587095},
{"learn":[4.297355825],"iteration":355,"passed_time":0.1908106074,"remaining_time":0.3451742449},
{"learn":[4.295758715],"iteration":356,"passed_time":0.1912167799,"remaining_time":0.3444044522},
{"learn":[4.292500657],"iteration":357,"passed_time":0.1915068119,"remaining_time":0.3434284169},
{"learn":[4.290797586],"iteration":358,"passed_time":0.1919295259,"remaining_time":0.3426931089},
{"learn":[4.286410608],"iteration":359,"passed_time":0.1922227288,"remaining_time":0.3417292957},
{"learn":[4.280278245],"iteration":360,"passed_time":0.1926244532,"remaining_time":0.3409612897},
{"learn":[4.279941283],"iteration":361,"passed_time":0.1929013443,"remaining_time":0.3399752975},
{"learn":[4.274426275],"iteration":362,"passed_time":0.1933458792,"remaining_time":0.3392873968},
{"learn":[4.273567658],"iteration":363,"passed_time":0.1936358955,"remaining_time":0.3383308504},
{"learn":[4.269488271],"iteration":364,"passed_time":0.1940335534,"remaining_time":0.337565223},
{"learn":[4.266838205],"iteration":365,"passed_time":0.194320852,"remaining_time":0.3366104376},
{"learn":[4.263456509],"iteration":366,"passed_time":0.1947585748,"remaining_time":0.3359187407},
{"learn":[4.260360204],"iteration":367,"passed_time":0.1950497903,"remaining_time":0.3349768137},
{"learn":[4.255120549],"iteration":368,"passed_time":0.195430623,"remaining_time":0.3341916616},
{"learn":[4.252582211],"iteration":369,"passed_time":0.1957199628,"remaining_time":0.3332529096},
{"learn":[4.247857931],"iteration":370,"passed_time":0.1961709997,"remaining_time":0.3325918028},
{"learn":[4.245288911],"iteration":371,"passed_time":0.1964689278,"remaining_time":0.3316733512},
{"learn":[4.24048515],"iteration":372,"passed_time":0.1969010785,"remaining_time":0.3309838504},
{"learn":[4.2378365],"iteration":373,"passed_time":0.1971923498,"remaining_time":0.3300599224},
{"learn":[4.236751063],"iteration":374,"passed_time":0.1976277587,"remaining_time":0.3293795978},
{"learn":[4.233240093],"iteration":375,"passed_time":0.1979250689,"remaining_time":0.3284713909},
{"learn":[4.230358421],"iteration":376,"passed_time":0.1983063069,"remaining_time":0.3277051172},
{"learn":[4.225853583],"iteration":377,"passed_time":0.1986050439,"remaining_time":0.3268051252},
{"learn":[4.224702126],"iteration":378,"passed_time":0.1990286063,"remaining_time":0.3261128352},
{"learn":[4.224361982],"iteration":379,"passed_time":0.1993171865,"remaining_time":0.3252017253},
{"learn":[4.223787954],"iteration":380,"passed_time":0.199681245,"remaining_time":0.324416511},
{"learn":[4.22144054],"iteration":381,"passed_time":0.2000020413,"remaining_time":0.3235635119},
{"learn":[4.217739335],"iteration":382,"passed_time":0.2003679627,"remaining_time":0.3227859869},
{"learn":[4.215611665],"iteration":383,"passed_time":0.2008002588,"remaining_time":0.3221170817},
{"learn":[4.210236863],"iteration":384,"passed_time":0.2011002673,"remaining_time":0.3212380893},
{"learn":[4.208454294],"iteration":385,"passed_time":0.2014968735,"remaining_time":0.3205157521},
{"learn":[4.207446501],"iteration":386,"passed_time":0.2017877875,"remaining_time":0.3196276841},
{"learn":[4.204985442],"iteration":387,"passed_time":0.2022249018,"remaining_time":0.3189732987},
{"learn":[4.202796622],"iteration":388,"passed_time":0.2025122176,"remaining_time":0.3180847428},
{"learn":[4.199774004],"iteration":389,"passed_time":0.2028892882,"remaining_time":0.3173396559},
{"learn":[4.199458358],"iteration":390,"passed_time":0.2031720729,"remaining_time":0.3164495968},
{"learn":[4.19751254],"iteration":391,"passed_time":0.203598194,"remaining_time":0.3157849539},
{"learn":[4.195201346],"iteration":392,"passed_time":0.2039123715,"remaining_time":0.3149486247},
{"learn":[4.190593508],"iteration":393,"passed_time":0.2042031087,"remaining_time":0.3140788931},
{"learn":[4.187212054],"iteration":394,"passed_time":0.2044898976,"remaining_time":0.3132060457},
{"learn":[4.184984466],"iteration":395,"passed_time":0.2047835802,"remaining_time":0.3123466728},
{"learn":[4.182832144],"iteration":396,"passed_time":0.2050758502,"remaining_time":0.3114880043},
{"learn":[4.179752812],"iteration":397,"passed_time":0.2053633758,"remaining_time":0.3106250056},
{"learn":[4.17878934],"iteration":398,"passed_time":0.2056444358,"remaining_time":0.3097551527},
{"learn":[4.174548229],"iteration":399,"passed_time":0.2059345853,"remaining_time":0.3089018779},
{"learn":[4.168872556],"iteration":400,"passed_time":0.2062221746,"remaining_time":0.3080475874},
{"learn":[4.163926494],"iteration":401,"passed_time":0.2065152937,"remaining_time":0.3072043424},
{"learn":[4.159485076],"iteration":402,"passed_time":0.2068191905,"remaining_time":0.3063797933},
{"learn":[4.155926102],"iteration":403,"passed_time":0.207112906,"remaining_time":0.3055428019},
{"learn":[4.153540115],"iteration":404,"passed_time":0.2073993526,"remaining_time":0.3046978144},
{"learn":[4.150983044],"iteration":405,"passed_time":0.2079658767,"remaining_time":0.3042653467},
{"learn":[4.146539132],"iteration":406,"passed_time":0.208853153,"remaining_time":0.3042995571},
{"learn":[4.144869174],"iteration":407,"passed_time":0.2094837947,"remaining_time":0.3039568786},
{"learn":[4.142825962],"iteration":408,"passed_time":0.2103707553,"remaining_time":0.3039831697},
{"learn":[4.142467378],"iteration":409,"passed_time":0.2111963521,"remaining_time":0.3039167018},
{"learn":[4.141800768],"iteration":410,"passed_time":0.2115283971,"remaining_time":0.3031392357},
{"learn":[4.140107084],"iteration":411,"passed_time":0.2118636394,"remaining_time":0.3023684951},
{"learn":[4.136243196],"iteration":412,"passed_time":0.2122027836,"remaining_time":0.3016054091},
{"learn":[4.133618439],"iteration":413,"passed_time":0.2125431119,"remaining_time":0.3008460473},
{"learn":[4.131053025],"iteration":414,"passed_time":0.212881621,"remaining_time":0.3000861405},
{"learn":[4.128379975],"iteration":415,"passed_time":0.213239045,"remaining_time":0.2993548132},
{"learn":[4.127068571],"iteration":416,"passed_time":0.2135873023,"remaining_time":0.2986124634},
{"learn":[4.125969877],"iteration":417,"passed_time":0.2139453678,"remaining_time":0.2978856556},
{"learn":[4.123893633],"iteration":418,"passed_time":0.2143263123,"remaining_time":0.2971923328},
{"learn":[4.119643722],"iteration":419,"passed_time":0.2147045527,"remaining_time":0.2964967632},
{"learn":[4.11465686],"iteration":420,"passed_time":0.2150671944,"remaining_time":0.2957812484},
{"learn":[4.111565986],"iteration":421,"passed_time":0.2154254296,"remaining_time":0.2950613704},
{"learn":[4.106322452],"iteration":422,"passed_time":0.2157979948,"remaining_time":0.2943627494},
{"learn":[4.104222175],"iteration":423,"passed_time":0.2161707755,"remaining_time":0.2936659592},
{"learn":[4.103008002],"iteration":424,"passed_time":0.2165333521,"remaining_time":0.2929568881},
{"learn":[4.099176337],"iteration":425,"passed_time":0.2169109167,"remaining_time":0.2922696389},
{"learn":[4.096525716],"iteration":426,"passed_time":0.2172860313,"remaining_time":0.2915805526},
{"learn":[4.094967724],"iteration":427,"passed_time":0.2176627633,"remaining_time":0.2908950948},
{"learn":[4.094683584],"iteration":428,"passed_time":0.2180472874,"remaining_time":0.2902214478},
{"learn":[4.091096563],"iteration":429,"passed_time":0.2184043227,"remaining_time":0.2895127068},
{"learn":[4.089178677],"iteration":430,"passed_time":0.2187781522,"remaining_time":0.2888277694},
{"learn":[4.085335077],"iteration":431,"passed_time":0.2191540501,"remaining_time":0.2881469918},
{"learn":[4.084852122],"iteration":432,"passed_time":0.2195305637,"remaining_time":0.2874684287},
{"learn":[4.080322952],"iteration":433,"passed_time":0.2198942543,"remaining_time":0.2867745344},
{"learn":[4.077449519],"iteration":434,"passed_time":0.2202719935,"remaining_time":0.2861004054},
{"learn":[4.076568374],"iteration":435,"passed_time":0.2206367967,"remaining_time":0.2854109021},
{"learn":[4.076071793],"iteration":436,"passed_time":0.2210198667,"remaining_time":0.2847464187},
{"learn":[4.075027644],"iteration":437,"passed_time":0.221400096,"remaining_time":0.2840795752},
{"learn":[4.07020837],"iteration":438,"passed_time":0.2217709158,"remaining_time":0.2834020131},
{"learn":[4.06833694],"iteration":439,"passed_time":0.2221490481,"remaining_time":0.2827351521},
{"learn":[4.063936568],"iteration":440,"passed_time":0.2225561477,"remaining_time":0.2821063187},
{"learn":[4.061734926],"iteration":441,"passed_time":0.2229492272,"remaining_time":0.2814607891},
{"learn":[4.060815619],"iteration":442,"passed_time":0.2233715202,"remaining_time":0.2808531304},
{"learn":[4.056407489],"iteration":443,"passed_time":0.2236756074,"remaining_time":0.2800982832},
{"learn":[4.05238936],"iteration":444,"passed_time":0.2240944196,"remaining_time":0.2794885458},
{"learn":[4.049685254],"iteration":445,"passed_time":0.2243897725,"remaining_time":0.2787263093},
{"learn":[4.045162016],"iteration":446,"passed_time":0.2248101175,"remaining_time":0.2781207941},
{"learn":[4.042955482],"iteration":447,"passed_time":0.225104138,"remaining_time":0.2773604557},
{"learn":[4.041467663],"iteration":448,"passed_time":0.2263441393,"remaining_time":0.2777630752},
{"learn":[4.038920476],"iteration":449,"passed_time":0.2266613595,"remaining_time":0.2770305505},
{"learn":[4.036694383],"iteration":450,"passed_time":0.2269521483,"remaining_time":0.2762676927},
{"learn":[4.034999007],"iteration":451,"passed_time":0.2272490518,"remaining_time":0.2755143372},
{"learn":[4.031928018],"iteration":452,"passed_time":0.2275357512,"remaining_time":0.2747506753},
{"learn":[4.028718143],"iteration":453,"passed_time":0.2278246371,"remaining_time":0.2739917441},
{"learn":[4.027401978],"iteration":454,"passed_time":0.2281086625,"remaining_time":0.2732290572},
{"learn":[4.025930598],"iteration":455,"passed_time":0.228399961,"remaining_time":0.2724771464},
{"learn":[4.021074523],"iteration":456,"passed_time":0.2287132629,"remaining_time":0.2717533956},
{"learn":[4.020268486],"iteration":457,"passed_time":0.2289931424,"remaining_time":0.2709918846},
{"learn":[4.017986361],"iteration":458,"passed_time":0.2292753564,"remaining_time":0.270235224},
{"learn":[4.014814804],"iteration":459,"passed_time":0.2295847888,"remaining_time":0.2695125781},
{"learn":[4.009704796],"iteration":460,"passed_time":0.2303409453,"remaining_time":0.2693140336},
{"learn":[4.008440457],"iteration":461,"passed_time":0.2307909678,"remaining_time":0.2687565815},
{"learn":[4.004854849],"iteration":462,"passed_time":0.2312235566,"remaining_time":0.2681793734},
{"learn":[4.000898028],"iteration":463,"passed_time":0.2322388077,"remaining_time":0.268275864},
{"learn":[3.996617985],"iteration":464,"passed_time":0.2326570901,"remaining_time":0.267680738},
{"learn":[3.995443319],"iteration":465,"passed_time":0.2329539027,"remaining_time":0.266947176},
{"learn":[3.990771995],"iteration":466,"passed_time":0.2334007994,"remaining_time":0.2663867796},
{"learn":[3.989249359],"iteration":467,"passed_time":0.2336995837,"remaining_time":0.2656585011},
{"learn":[3.986599538],"iteration":468,"passed_time":0.2340908233,"remaining_time":0.2650367317},
{"learn":[3.985628919],"iteration":469,"passed_time":0.234378462,"remaining_time":0.2642991167},
{"learn":[3.985086112],"iteration":470,"passed_time":0.2348007493,"remaining_time":0.263714642},
{"learn":[3.98466839],"iteration":471,"passed_time":0.2350938842,"remaining_time":0.2629863789},
{"learn":[3.984233894],"iteration":472,"passed_time":0.2354837441,"remaining_time":0.2623677234},
{"learn":[3.981855845],"iteration":473,"passed_time":0.235794584,"remaining_time":0.2616623443},
{"learn":[3.978684264],"iteration":474,"passed_time":0.2362389191,"remaining_time":0.2611061737},
{"learn":[3.974361269],"iteration":475,"passed_time":0.2365382883,"remaining_time":0.2603908888},
{"learn":[3.972074049],"iteration":476,"passed_time":0.2369397406,"remaining_time":0.2597892754},
{"learn":[3.97191982],"iteration":477,"passed_time":0.2372215609,"remaining_time":0.2590578553},
{"learn":[3.969616848],"iteration":478,"passed_time":0.2376481839,"remaining_time":0.2584858118},
{"learn":[3.968533527],"iteration":479,"passed_time":0.2379357124,"remaining_time":0.2577636884},
{"learn":[3.967568753],"iteration":480,"passed_time":0.2383066925,"remaining_time":0.2571334167},
{"learn":[3.966232553],"iteration":481,"passed_time":0.2385997644,"remaining_time":0.2564204937},
{"learn":[3.961522393],"iteration":482,"passed_time":0.2390395362,"remaining_time":0.2558663359},
{"learn":[3.955829553],"iteration":483,"passed_time":0.2393331808,"remaining_time":0.2551568622},
{"learn":[3.954248095],"iteration":484,"passed_time":0.2397227315,"remaining_time":0.2545509417},
{"learn":[3.951922606],"iteration":485,"passed_time":0.2400190745,"remaining_time":0.2538473339},
{"learn":[3.94978202],"iteration":486,"passed_time":0.2404644842,"remaining_time":0.2533024238},
{"learn":[3.949518999],"iteration":487,"passed_time":0.2407550453,"remaining_time":0.2525954574},
{"learn":[3.945431216],"iteration":488,"passed_time":0.2411316928,"remaining_time":0.2519801534},
{"learn":[3.943249086],"iteration":489,"passed_time":0.2414291605,"remaining_time":0.251283412},
{"learn":[3.941981548],"iteration":490,"passed_time":0.2418597455,"remaining_time":0.2507262942},
{"learn":[3.936600517],"iteration":491,"passed_time":0.242162748,"remaining_time":0.2500379593},
{"learn":[3.934476885],"iteration":492,"passed_time":0.2425529137,"remaining_time":0.2494408261},
{"learn":[3.93045798],"iteration":493,"passed_time":0.2428453821,"remaining_time":0.2487444602},
{"learn":[3.925977375],"iteration":494,"passed_time":0.2432898718,"remaining_time":0.2482048187},
{"learn":[3.92457993],"iteration":495,"passed_time":0.2435816099,"remaining_time":0.2475103456},
{"learn":[3.919849146],"iteration":496,"passed_time":0.2439577312,"remaining_time":0.2469028949},
{"learn":[3.919681964],"iteration":497,"passed_time":0.2442412669,"remaining_time":0.2462030441},
{"learn":[3.917633027],"iteration":498,"passed_time":0.2446742538,"remaining_time":0.2456549121},
{"learn":[3.916616419],"iteration":499,"passed_time":0.2449661057,"remaining_time":0.2449661057},
{"learn":[3.912896166],"iteration":500,"passed_time":0.2453633555,"remaining_time":0.2443838611},
{"learn":[3.912769674],"iteration":501,"passed_time":0.2456425913,"remaining_time":0.2436852798},
{"learn":[3.909373788],"iteration":502,"passed_time":0.2460942003,"remaining_time":0.243158683},
{"learn":[3.906706036],"iteration":503,"passed_time":0.2463858704,"remaining_time":0.2424749836},
{"learn":[3.903895664],"iteration":504,"passed_time":0.2467768544,"remaining_time":0.241890184},
{"learn":[3.902982967],"iteration":505,"passed_time":0.2470674749,"remaining_time":0.2412081672},
{"learn":[3.900905528],"iteration":506,"passed_time":0.2490641074,"remaining_time":0.2421865976},
{"learn":[3.897463465],"iteration":507,"passed_time":0.2509388696,"remaining_time":0.2430352831},
{"learn":[3.895918033],"iteration":508,"passed_time":0.251280667,"remaining_time":0.2423945137},
{"learn":[3.893921936],"iteration":509,"passed_time":0.2516447434,"remaining_time":0.2417763221},
{"learn":[3.890237934],"iteration":510,"passed_time":0.2520049904,"remaining_time":0.2411554604},
{"learn":[3.887311613],"iteration":511,"passed_time":0.2523691119,"remaining_time":0.2405393098},
{"learn":[3.884869735],"iteration":512,"passed_time":0.2531150084,"remaining_time":0.2402865674},
{"learn":[3.882101231],"iteration":513,"passed_time":0.2534926832,"remaining_time":0.2396837433},
{"learn":[3.88060368],"iteration":514,"passed_time":0.2538682203,"remaining_time":0.2390797803},
{"learn":[3.877726076],"iteration":515,"passed_time":0.2542254503,"remaining_time":0.2384595309},
{"learn":[3.874938145],"iteration":516,"passed_time":0.2546037752,"remaining_time":0.2378600066},
{"learn":[3.874340833],"iteration":517,"passed_time":0.2549614985,"remaining_time":0.2372421665},
{"learn":[3.873105224],"iteration":518,"passed_time":0.2553125435,"remaining_time":0.2366191396},
{"learn":[3.869800236],"iteration":519,"passed_time":0.2556953215,"remaining_time":0.2360264506},
{"learn":[3.867932518],"iteration":520,"passed_time":0.2560685877,"remaining_time":0.2354258224},
{"learn":[3.866666962],"iteration":521,"passed_time":0.2564674812,"remaining_time":0.2348495326},
{"learn":[3.865527652],"iteration":522,"passed_time":0.2568607934,"remaining_time":0.2342688307},
{"learn":[3.861900081],"iteration":523,"passed_time":0.2572545108,"remaining_time":0.2336892121},
{"learn":[3.858502887],"iteration":524,"passed_time":0.2576878743,"remaining_time":0.233146172},
{"learn":[3.858335097],"iteration":525,"passed_time":0.2580783249,"remaining_time":0.2325648783},
{"learn":[3.855719306],"iteration":526,"passed_time":0.2584742552,"remaining_time":0.2319892272},
{"learn":[3.855137428],"iteration":527,"passed_time":0.2588669481,"remaining_time":0.2314113627},
{"learn":[3.851985706],"iteration":528,"passed_time":0.2592725378,"remaining_time":0.2308456811},
{"learn":[3.851051809],"iteration":529,"passed_time":0.2596599128,"remaining_time":0.230264451},
{"learn":[3.850679146],"iteration":530,"passed_time":0.2600451206,"remaining_time":0.2296820369},
{"learn":[3.848179484],"iteration":531,"passed_time":0.2603949644,"remaining_time":0.2290692544},
{"learn":[3.844551071],"iteration":532,"passed_time":0.2607542312,"remaining_time":0.2284657148},
{"learn":[3.841604794],"iteration":533,"passed_time":0.2611592209,"remaining_time":0.2279029906},
{"learn":[3.83969656],"iteration":534,"passed_time":0.2614526236,"remaining_time":0.2272438691},
{"learn":[3.836811463],"iteration":535,"passed_time":0.2618947035,"remaining_time":0.226714818},
{"learn":[3.834182551],"iteration":536,"passed_time":0.2621867631,"remaining_time":0.2260567436},
{"learn":[3.828012842],"iteration":537,"passed_time":0.2626261841,"remaining_time":0.2255265744},
{"learn":[3.826636176],"iteration":538,"passed_time":0.2629121231,"remaining_time":0.2248654708},
{"learn":[3.826189798],"iteration":539,"passed_time":0.2633149858,"remaining_time":0.2243053583},
{"learn":[3.824104738],"iteration":540,"passed_time":0.2636096206,"remaining_time":0.2236540034},
{"learn":[3.82300218],"iteration":541,"passed_time":0.2640214446,"remaining_time":0.2231029919},
{"learn":[3.817146402],"iteration":542,"passed_time":0.2643078762,"remaining_time":0.2224469603},
{"learn":[3.814638044],"iteration":543,"passed_time":0.2647356189,"remaining_time":0.2219107394},
{"learn":[3.812979573],"iteration":544,"passed_time":0.2650331697,"remaining_time":0.2212662242},
{"learn":[3.811938825],"iteration":545,"passed_time":0.2654381494,"remaining_time":0.2207123074},
{"learn":[3.811479418],"iteration":546,"passed_time":0.2657204945,"remaining_time":0.2200573748},
{"learn":[3.80742981],"iteration":547,"passed_time":0.2661399732,"remaining_time":0.2195169122},
{"learn":[3.805097043],"iteration":548,"passed_time":0.2664368954,"remaining_time":0.2188762109},
{"learn":[3.801577232],"iteration":549,"passed_time":0.2668607928,"remaining_time":0.2183406487},
{"learn":[3.799762083],"iteration":550,"passed_time":0.2671519567,"remaining_time":0.2176973295},
{"learn":[3.796393455],"iteration":551,"passed_time":0.267568919,"remaining_time":0.2171573835},
{"learn":[3.793486459],"iteration":552,"passed_time":0.2678593054,"remaining_time":0.2165155687},
{"learn":[3.792006091],"iteration":553,"passed_time":0.2682905884,"remaining_time":0.215988452},
{"learn":[3.78932128],"iteration":554,"passed_time":0.2685850048,"remaining_time":0.2153519408},
{"learn":[3.787581812],"iteration":555,"passed_time":0.2689985742,"remaining_time":0.2148118111},
{"learn":[3.785308865],"iteration":556,"passed_time":0.2692936106,"remaining_time":0.2141778627},
{"learn":[3.78465475],"iteration":557,"passed_time":0.2697122209,"remaining_time":0.2136430137},
{"learn":[3.780498869],"iteration":558,"passed_time":0.2700008949,"remaining_time":0.2130060727},
{"learn":[3.778734909],"iteration":559,"passed_time":0.270390956,"remaining_time":0.2124500369},
{"learn":[3.778652349],"iteration":560,"passed_time":0.2706722487,"remaining_time":0.211809478},
{"learn":[3.777928006],"iteration":561,"passed_time":0.2710986154,"remaining_time":0.2112832625},
{"learn":[3.776131406],"iteration":562,"passed_time":0.2713852024,"remaining_time":0.2106489049},
{"learn":[3.772925617],"iteration":563,"passed_time":0.2717669136,"remaining_time":0.2100893162},
{"learn":[3.7727745],"iteration":564,"passed_time":0.2720749091,"remaining_time":0.2094736026},
{"learn":[3.771763073],"iteration":565,"passed_time":0.2725061047,"remaining_time":0.2089534443},
{"learn":[3.768738162],"iteration":566,"passed_time":0.2727998811,"remaining_time":0.208328657},
{"learn":[3.767220794],"iteration":567,"passed_time":0.2731909481,"remaining_time":0.207779031},
{"learn":[3.766691102],"iteration":568,"passed_time":0.2734834902,"remaining_time":0.2071553327},
{"learn":[3.766259335],"iteration":569,"passed_time":0.2739151684,"remaining_time":0.2066377586},
{"learn":[3.76116362],"iteration":570,"passed_time":0.2742026338,"remaining_time":0.2060121364},
{"learn":[3.758633056],"iteration":571,"passed_time":0.2745885576,"remaining_time":0.2054613683},
{"learn":[3.754603809],"iteration":572,"passed_time":0.2748881717,"remaining_time":0.2048468574},
{"learn":[3.754070549],"iteration":573,"passed_time":0.2753117806,"remaining_time":0.2043254678},
{"learn":[3.750534319],"iteration":574,"passed_time":0.275616079,"remaining_time":0.2037162323},
{"learn":[3.746491516],"iteration":575,"passed_time":0.2760278615,"remaining_time":0.2031871758},
{"learn":[3.744210544],"iteration":576,"passed_time":0.276321141,"remaining_time":0.202571651},
{"learn":[3.742929991],"iteration":577,"passed_time":0.2767519758,"remaining_time":0.2020576709},
{"learn":[3.740402992],"iteration":578,"passed_time":0.2770383795,"remaining_time":0.2014389599},
{"learn":[3.739644243],"iteration":579,"passed_time":0.2774207838,"remaining_time":0.2008909124},
{"learn":[3.737529404],"iteration":580,"passed_time":0.2777174453,"remaining_time":0.2002816},
{"learn":[3.737196923],"iteration":581,"passed_time":0.2781420952,"remaining_time":0.1997652849},
{"learn":[3.733954464],"iteration":582,"passed_time":0.2784380602,"remaining_time":0.1991572403},
{"learn":[3.731608623],"iteration":583,"passed_time":0.2788295725,"remaining_time":0.1986183256},
{"learn":[3.729843952],"iteration":584,"passed_time":0.2791283339,"remaining_time":0.1980141172},
{"learn":[3.727223798],"iteration":585,"passed_time":0.2795830951,"remaining_time":0.1975211628},
{"learn":[3.725351667],"iteration":586,"passed_time":0.2798719466,"remaining_time":0.1969116081},
{"learn":[3.725026912],"iteration":587,"passed_time":0.2802676364,"remaining_time":0.1963780037},
{"learn":[3.721974565],"iteration":588,"passed_time":0.2805604455,"remaining_time":0.1957730783},
{"learn":[3.720269493],"iteration":589,"passed_time":0.2809947147,"remaining_time":0.1952675136},
{"learn":[3.718907466],"iteration":590,"passed_time":0.2812848004,"remaining_time":0.1946624084},
{"learn":[3.715602912],"iteration":591,"passed_time":0.281665674,"remaining_time":0.1941209375},
{"learn":[3.714463059],"iteration":592,"passed_time":0.2819466023,"remaining_time":0.1935114117},
{"learn":[3.710802077],"iteration":593,"passed_time":0.2823787608,"remaining_time":0.1930063584},
{"learn":[3.708032435],"iteration":594,"passed_time":0.2826720504,"remaining_time":0.1924070259},
{"learn":[3.703788939],"iteration":595,"passed_time":0.2830873259,"remaining_time":0.1918914088},
{"learn":[3.702500944],"iteration":596,"passed_time":0.2833776665,"remaining_time":0.1912917916},
{"learn":[3.698196925],"iteration":597,"passed_time":0.2838111517,"remaining_time":0.1907894364},
{"learn":[3.69658891],"iteration":598,"passed_time":0.2841041305,"remaining_time":0.1901932493},
{"learn":[3.696124066],"iteration":599,"passed_time":0.2844746331,"remaining_time":0.1896497554},
{"learn":[3.693537052],"iteration":600,"passed_time":0.2847654183,"remaining_time":0.1890539133},
{"learn":[3.691343275],"iteration":601,"passed_time":0.2851938641,"remaining_time":0.1885500962},
{"learn":[3.690973831],"iteration":602,"passed_time":0.2854816431,"remaining_time":0.1879539176},
{"learn":[3.686151073],"iteration":603,"passed_time":0.2858752023,"remaining_time":0.1874281128},
{"learn":[3.683921982],"iteration":604,"passed_time":0.2861627157,"remaining_time":0.1868335086},
{"learn":[3.679975271],"iteration":605,"passed_time":0.2866037625,"remaining_time":0.18633974},
{"learn":[3.674047638],"iteration":606,"passed_time":0.286903227,"remaining_time":0.1857544781},
{"learn":[3.673151794],"iteration":607,"passed_time":0.2872750791,"remaining_time":0.1852168273},
{"learn":[3.670953108],"iteration":608,"passed_time":0.2875674995,"remaining_time":0.184628723},
{"learn":[3.6703947],"iteration":609,"passed_time":0.2879976155,"remaining_time":0.1841296231},
{"learn":[3.668433805],"iteration":610,"passed_time":0.2882914714,"remaining_time":0.1835439973},
{"learn":[3.668304956],"iteration":611,"passed_time":0.2886609588,"remaining_time":0.1830072745},
{"learn":[3.667880012],"iteration":612,"passed_time":0.2889486627,"remaining_time":0.1824194657},
{"learn":[3.667282264],"iteration":613,"passed_time":0.2893731207,"remaining_time":0.1819186068},
{"learn":[3.664611483],"iteration":614,"passed_time":0.2896637806,"remaining_time":0.1813342366},
{"learn":[3.662543394],"iteration":615,"passed_time":0.2900595792,"remaining_time":0.1808163611},
{"learn":[3.659041959],"iteration":616,"passed_time":0.2903832185,"remaining_time":0.1802540886},
{"learn":[3.656868545],"iteration":617,"passed_time":0.2908246355,"remaining_time":0.1797653896},
{"learn":[3.654785614],"iteration":618,"passed_time":0.2911164423,"remaining_time":0.1791847569},
{"learn":[3.654566096],"iteration":619,"passed_time":0.2915075866,"remaining_time":0.1786659402},
{"learn":[3.651007045],"iteration":620,"passed_time":0.2917987463,"remaining_time":0.1780865134},
{"learn":[3.648921786],"iteration":621,"passed_time":0.2922459938,"remaining_time":0.1776028708},
{"learn":[3.647655706],"iteration":622,"passed_time":0.2925398554,"remaining_time":0.1770265256},
{"learn":[3.647241144],"iteration":623,"passed_time":0.2929159057,"remaining_time":0.1765006099},
{"learn":[3.644195689],"iteration":624,"passed_time":0.2932081035,"remaining_time":0.1759248621},
{"learn":[3.642632246],"iteration":625,"passed_time":0.2936416431,"remaining_time":0.1754344641},
{"learn":[3.642523322],"iteration":626,"passed_time":0.293867507,"remaining_time":0.1748207019},
{"learn":[3.641494659],"iteration":627,"passed_time":0.2942086951,"remaining_time":0.1742764882},
{"learn":[3.63976496],"iteration":628,"passed_time":0.2945808967,"remaining_time":0.1737512125},
{"learn":[3.637945652],"iteration":629,"passed_time":0.2948786815,"remaining_time":0.1731827177},
{"learn":[3.636233667],"iteration":630,"passed_time":0.2953068252,"remaining_time":0.172691313},
{"learn":[3.635304404],"iteration":631,"passed_time":0.2955941281,"remaining_time":0.1721180999},
{"learn":[3.632234951],"iteration":632,"passed_time":0.2959930897,"remaining_time":0.1716105275},
{"learn":[3.631630987],"iteration":633,"passed_time":0.2962906712,"remaining_time":0.1710447723},
{"learn":[3.630301009],"iteration":634,"passed_time":0.2967207006,"remaining_time":0.1705559933},
{"learn":[3.629077964],"iteration":635,"passed_time":0.2970063998,"remaining_time":0.1699847949},
{"learn":[3.628004522],"iteration":636,"passed_time":0.2973965598,"remaining_time":0.1694740207},
{"learn":[3.625062876],"iteration":637,"passed_time":0.2976933123,"remaining_time":0.1689106255},
{"learn":[3.624917986],"iteration":638,"passed_time":0.2981137868,"remaining_time":0.168417961},
{"learn":[3.622887087],"iteration":639,"passed_time":0.2984114314,"remaining_time":0.1678564302},
{"learn":[3.621220865],"iteration":640,"passed_time":0.2988246156,"remaining_time":0.1673604322},
{"learn":[3.621143844],"iteration":641,"passed_time":0.2991111933,"remaining_time":0.1667940922},
{"learn":[3.620822821],"iteration":642,"passed_time":0.2995296826,"remaining_time":0.1663018611},
{"learn":[3.619202826],"iteration":643,"passed_time":0.2998136701,"remaining_time":0.1657355071},
{"learn":[3.618204882],"iteration":644,"passed_time":0.3002049748,"remaining_time":0.1652290947},
{"learn":[3.614259666],"iteration":645,"passed_time":0.3004997785,"remaining_time":0.1646701573},
{"learn":[3.613415661],"iteration":646,"passed_time":0.3024162293,"remaining_time":0.164996799},
{"learn":[3.611096773],"iteration":647,"passed_time":0.3027198146,"remaining_time":0.1644403931},
{"learn":[3.610820695],"iteration":648,"passed_time":0.3030145797,"remaining_time":0.1638799961},
{"learn":[3.609290065],"iteration":649,"passed_time":0.3039084082,"remaining_time":0.163642989},
{"learn":[3.60897947],"iteration":650,"passed_time":0.3043288935,"remaining_time":0.1631502056},
{"learn":[3.606570702],"iteration":651,"passed_time":0.3046331998,"remaining_time":0.1625956343},
{"learn":[3.606292637],"iteration":652,"passed_time":0.3050804101,"remaining_time":0.1621177677},
{"learn":[3.602753838],"iteration":653,"passed_time":0.305403289,"remaining_time":0.1615742171},
{"learn":[3.599755869],"iteration":654,"passed_time":0.3058175715,"remaining_time":0.1610794842},
{"learn":[3.599509575],"iteration":655,"passed_time":0.3061102984,"remaining_time":0.160521254},
{"learn":[3.595337722],"iteration":656,"passed_time":0.3065634122,"remaining_time":0.1600475653},
{"learn":[3.595168561],"iteration":657,"passed_time":0.3068519766,"remaining_time":0.1594884134},
{"learn":[3.59290559],"iteration":658,"passed_time":0.3072356037,"remaining_time":0.1589792729},
{"learn":[3.592015928],"iteration":659,"passed_time":0.3075324056,"remaining_time":0.1584257847},
{"learn":[3.590680403],"iteration":660,"passed_time":0.3079553616,"remaining_time":0.1579377724},
{"learn":[3.590361532],"iteration":661,"passed_time":0.3082482989,"remaining_time":0.1573835725},
{"learn":[3.589069739],"iteration":662,"passed_time":0.3085661949,"remaining_time":0.1568428472},
{"learn":[3.585010186],"iteration":663,"passed_time":0.3089924571,"remaining_time":0.1563576289},
{"learn":[3.582997552],"iteration":664,"passed_time":0.3092895733,"remaining_time":0.1558075294},
{"learn":[3.582119256],"iteration":665,"passed_time":0.3097196105,"remaining_time":0.1553248497},
{"learn":[3.579019356],"iteration":666,"passed_time":0.310015965,"remaining_time":0.1547755867},
{"learn":[3.57719559],"iteration":667,"passed_time":0.3104261624,"remaining_time":0.1542836615},
{"learn":[3.574050046],"iteration":668,"passed_time":0.3107160076,"remaining_time":0.1537324342},
{"learn":[3.572204518],"iteration":669,"passed_time":0.3111544828,"remaining_time":0.153255193},
{"learn":[3.569508025],"iteration":670,"passed_time":0.3114583409,"remaining_time":0.1527120628},
{"learn":[3.566268704],"iteration":671,"passed_time":0.3118815704,"remaining_time":0.1522279093},
{"learn":[3.562564052],"iteration":672,"passed_time":0.3121859719,"remaining_time":0.1516862003},
{"learn":[3.561173586],"iteration":673,"passed_time":0.3126256148,"remaining_time":0.1512106089},
{"learn":[3.559551904],"iteration":674,"passed_time":0.312929107,"remaining_time":0.15066957},
{"learn":[3.558593054],"iteration":675,"passed_time":0.3133138746,"remaining_time":0.1501681884},
{"learn":[3.555647008],"iteration":676,"passed_time":0.3139321557,"remaining_time":0.1497785618},
{"learn":[3.553100059],"iteration":677,"passed_time":0.314388691,"remaining_time":0.1493114432},
{"learn":[3.55085578],"iteration":678,"passed_time":0.3146868582,"remaining_time":0.1487694867},
{"learn":[3.550737965],"iteration":679,"passed_time":0.3150527875,"remaining_time":0.1482601353},
{"learn":[3.549408772],"iteration":680,"passed_time":0.3153463025,"remaining_time":0.1477172841},
{"learn":[3.547390589],"iteration":681,"passed_time":0.3157986553,"remaining_time":0.1472492264},
{"learn":[3.54723575],"iteration":682,"passed_time":0.3160875068,"remaining_time":0.1467053289},
{"learn":[3.543988891],"iteration":683,"passed_time":0.3164680654,"remaining_time":0.1462045448},
{"learn":[3.543868508],"iteration":684,"passed_time":0.3167555989,"remaining_time":0.1456613338},
{"learn":[3.542752124],"iteration":685,"passed_time":0.3177927373,"remaining_time":0.1454619818},
{"learn":[3.541334315],"iteration":686,"passed_time":0.3181120581,"remaining_time":0.1449331502},
{"learn":[3.540208266],"iteration":687,"passed_time":0.3185387799,"remaining_time":0.1444536327},
{"learn":[3.537730983],"iteration":688,"passed_time":0.3188364094,"remaining_time":0.143915999},
{"learn":[3.53419867],"iteration":689,"passed_time":0.3192796198,"remaining_time":0.1434444669},
{"learn":[3.532628335],"iteration":690,"passed_time":0.3195768971,"remaining_time":0.1429077586},
{"learn":[3.532204987],"iteration":691,"passed_time":0.3199953019,"remaining_time":0.1424256546},
{"learn":[3.530618147],"iteration":692,"passed_time":0.3202885921,"remaining_time":0.1418883085},
{"learn":[3.528909306],"iteration":693,"passed_time":0.3207332265,"remaining_time":0.1414183967},
{"learn":[3.526700678],"iteration":694,"passed_time":0.3210333138,"remaining_time":0.1408851233},
{"learn":[3.526439574],"iteration":695,"passed_time":0.3214213245,"remaining_time":0.1403909234},
{"learn":[3.525784216],"iteration":696,"passed_time":0.3217207066,"remaining_time":0.1398584994},
{"learn":[3.524112693],"iteration":697,"passed_time":0.3221755573,"remaining_time":0.139394009},
{"learn":[3.522813541],"iteration":698,"passed_time":0.3224715166,"remaining_time":0.1388611252},
{"learn":[3.519148203],"iteration":699,"passed_time":0.3228689955,"remaining_time":0.1383724266},
{"learn":[3.517236747],"iteration":700,"passed_time":0.3231704366,"remaining_time":0.137843025},
{"learn":[3.515603888],"iteration":701,"passed_time":0.3236221343,"remaining_time":0.137378057},
{"learn":[3.51263524],"iteration":702,"passed_time":0.3239216124,"remaining_time":0.1368488177},
{"learn":[3.51123442],"iteration":703,"passed_time":0.3243206849,"remaining_time":0.1363621062},
{"learn":[3.50828027],"iteration":704,"passed_time":0.3246179321,"remaining_time":0.1358330354},
{"learn":[3.508265537],"iteration":705,"passed_time":0.3248318307,"remaining_time":0.1352699125},
{"learn":[3.506774876],"iteration":706,"passed_time":0.3251335209,"remaining_time":0.1347441607},
{"learn":[3.50552068],"iteration":707,"passed_time":0.3255713654,"remaining_time":0.1342751959},
{"learn":[3.501973993],"iteration":708,"passed_time":0.325864471,"remaining_time":0.1337469126},
{"learn":[3.498880354],"iteration":709,"passed_time":0.326245268,"remaining_time":0.1332551094},
{"learn":[3.497370959],"iteration":710,"passed_time":0.3265610155,"remaining_time":0.1327371779},
{"learn":[3.496050455],"iteration":711,"passed_time":0.3270035672,"remaining_time":0.1322711059},
{"learn":[3.495630067],"iteration":712,"passed_time":0.327303492,"remaining_time":0.1317476889},
{"learn":[3.49550669],"iteration":713,"passed_time":0.3276820632,"remaining_time":0.1312564007},
{"learn":[3.493652375],"iteration":714,"passed_time":0.3279850794,"remaining_time":0.1307353114},
{"learn":[3.491915684],"iteration":715,"passed_time":0.3284159063,"remaining_time":0.1302655271},
{"learn":[3.490303956],"iteration":716,"passed_time":0.3287047657,"remaining_time":0.1297398168},
{"learn":[3.488363853],"iteration":717,"passed_time":0.3291091719,"remaining_time":0.1292601483},
{"learn":[3.485483936],"iteration":718,"passed_time":0.3294189285,"remaining_time":0.1287436981},
{"learn":[3.483763466],"iteration":719,"passed_time":0.3298535821,"remaining_time":0.1282763931},
{"learn":[3.481642352],"iteration":720,"passed_time":0.3301547032,"remaining_time":0.1277575065},
{"learn":[3.479826119],"iteration":721,"passed_time":0.3305590085,"remaining_time":0.1272789534},
{"learn":[3.478588728],"iteration":722,"passed_time":0.3308587464,"remaining_time":0.1267605432},
{"learn":[3.475390887],"iteration":723,"passed_time":0.3312990859,"remaining_time":0.1262963366},
{"learn":[3.472636852],"iteration":724,"passed_time":0.3315904253,"remaining_time":0.1257756786},
{"learn":[3.47061883],"iteration":725,"passed_time":0.3319856605,"remaining_time":0.1252948636},
{"learn":[3.46953149],"iteration":726,"passed_time":0.3322798327,"remaining_time":0.1247763333},
{"learn":[3.467217162],"iteration":727,"passed_time":0.3327178297,"remaining_time":0.1243121562},
{"learn":[3.465686216],"iteration":728,"passed_time":0.3330115645,"remaining_time":0.1237944225},
{"learn":[3.462631216],"iteration":729,"passed_time":0.333421792,"remaining_time":0.1233203888},
{"learn":[3.461451053],"iteration":730,"passed_time":0.3337393358,"remaining_time":0.1228124232},
{"learn":[3.458950469],"iteration":731,"passed_time":0.3340319488,"remaining_time":0.1222958501},
{"learn":[3.458072145],"iteration":732,"passed_time":0.3343186618,"remaining_time":0.121777739},
{"learn":[3.454364268],"iteration":733,"passed_time":0.3346156835,"remaining_time":0.1212639943},
{"learn":[3.453243406],"iteration":734,"passed_time":0.3349121868,"remaining_time":0.1207506524},
{"learn":[3.453017963],"iteration":735,"passed_time":0.3351969131,"remaining_time":0.1202336754},
{"learn":[3.45201581],"iteration":736,"passed_time":0.3354778815,"remaining_time":0.1197159876},
{"learn":[3.449510107],"iteration":737,"passed_time":0.3357663392,"remaining_time":0.1192016001},
{"learn":[3.447189189],"iteration":738,"passed_time":0.336060888,"remaining_time":0.1186899753},
{"learn":[3.446423605],"iteration":739,"passed_time":0.336343337,"remaining_time":0.118174686},
{"learn":[3.445531987],"iteration":740,"passed_time":0.3366310923,"remaining_time":0.1176618798},
{"learn":[3.445328199],"iteration":741,"passed_time":0.3369119125,"remaining_time":0.1171472688},
{"learn":[3.443327544],"iteration":742,"passed_time":0.3372051211,"remaining_time":0.1166375722},
{"learn":[3.441475798],"iteration":743,"passed_time":0.337774413,"remaining_time":0.1162234539},
{"learn":[3.439046501],"iteration":744,"passed_time":0.338393355,"remaining_time":0.1158259134},
{"learn":[3.435899469],"iteration":745,"passed_time":0.3392441267,"remaining_time":0.1155067134},
{"learn":[3.433988352],"iteration":746,"passed_time":0.340035366,"remaining_time":0.1151659272},
{"learn":[3.433413263],"iteration":747,"passed_time":0.3409358154,"remaining_time":0.1148607293},
{"learn":[3.429944699],"iteration":748,"passed_time":0.3417355771,"remaining_time":0.1145202001},
{"learn":[3.429291634],"iteration":749,"passed_time":0.3420743289,"remaining_time":0.1140247763},
{"learn":[3.429175603],"iteration":750,"passed_time":0.3424176763,"remaining_time":0.1135312935},
{"learn":[3.428780323],"iteration":751,"passed_time":0.3427524762,"remaining_time":0.1130353911},
{"learn":[3.423893341],"iteration":752,"passed_time":0.3430935018,"remaining_time":0.1125419588},
{"learn":[3.421024316],"iteration":753,"passed_time":0.3434277999,"remaining_time":0.1120467358},
{"learn":[3.420969872],"iteration":754,"passed_time":0.3437687432,"remaining_time":0.1115540955},
{"learn":[3.419544785],"iteration":755,"passed_time":0.3441157812,"remaining_time":0.1110638236},
{"learn":[3.417057977],"iteration":756,"passed_time":0.3444718263,"remaining_time":0.1105768214},
{"learn":[3.415160245],"iteration":757,"passed_time":0.3448359099,"remaining_time":0.1100927311},
{"learn":[3.412854597],"iteration":758,"passed_time":0.3452094703,"remaining_time":0.1096119662},
{"learn":[3.410926347],"iteration":759,"passed_time":0.3455849436,"remaining_time":0.1091320875},
{"learn":[3.408963843],"iteration":760,"passed_time":0.3459566505,"remaining_time":0.1086513002},
{"learn":[3.407629634],"iteration":761,"passed_time":0.3463252867,"remaining_time":0.1081698402},
{"learn":[3.404384724],"iteration":762,"passed_time":0.3467044614,"remaining_time":0.1076919493},
{"learn":[3.403041656],"iteration":763,"passed_time":0.3470739954,"remaining_time":0.1072113389},
{"learn":[3.401101731],"iteration":764,"passed_time":0.3474439933,"remaining_time":0.1067311613},
{"learn":[3.400890668],"iteration":765,"passed_time":0.3478264126,"remaining_time":0.106255066},
{"learn":[3.399289941],"iteration":766,"passed_time":0.3481952084,"remaining_time":0.1057750764},
{"learn":[3.399202366],"iteration":767,"passed_time":0.3485571865,"remaining_time":0.1052933167},
{"learn":[3.397447845],"iteration":768,"passed_time":0.3489184958,"remaining_time":0.1048116678},
{"learn":[3.394655341],"iteration":769,"passed_time":0.3493022024,"remaining_time":0.1043370215},
{"learn":[3.393228229],"iteration":770,"passed_time":0.3496885844,"remaining_time":0.1038634057},
{"learn":[3.389691197],"iteration":771,"passed_time":0.3500635881,"remaining_time":0.1033866555},
{"learn":[3.389626772],"iteration":772,"passed_time":0.3504643588,"remaining_time":0.1029177354},
{"learn":[3.388480222],"iteration":773,"passed_time":0.3508253933,"remaining_time":0.1024373887},
{"learn":[3.388215066],"iteration":774,"passed_time":0.3512010921,"remaining_time":0.1019616074},
{"learn":[3.386324358],"iteration":775,"passed_time":0.3515638119,"remaining_time":0.1014823374},
{"learn":[3.383913061],"iteration":776,"passed_time":0.3519385571,"remaining_time":0.1010068188},
{"learn":[3.382839768],"iteration":777,"passed_time":0.3523109985,"remaining_time":0.1005309019},
{"learn":[3.381961844],"iteration":778,"passed_time":0.3526860559,"remaining_time":0.1000559927},
{"learn":[3.381521703],"iteration":779,"passed_time":0.3530550894,"remaining_time":0.09957964061},
{"learn":[3.380918963],"iteration":780,"passed_time":0.3534146376,"remaining_time":0.0991009035},
{"learn":[3.377139006],"iteration":781,"passed_time":0.3537910989,"remaining_time":0.09862718615},
{"learn":[3.376004372],"iteration":782,"passed_time":0.3541643307,"remaining_time":0.09815282217},
{"learn":[3.373826468],"iteration":783,"passed_time":0.3545449136,"remaining_time":0.09768074151},
{"learn":[3.373546786],"iteration":784,"passed_time":0.3550214449,"remaining_time":0.0972351728},
{"learn":[3.372109181],"iteration":785,"passed_time":0.3554168025,"remaining_time":0.09676742459},
{"learn":[3.370764924],"iteration":786,"passed_time":0.3558006393,"remaining_time":0.09629674228},
{"learn":[3.367833107],"iteration":787,"passed_time":0.3561918853,"remaining_time":0.09582827371},
{"learn":[3.36450404],"iteration":788,"passed_time":0.3565679887,"remaining_time":0.09535595134},
{"learn":[3.361794558],"iteration":789,"passed_time":0.3569434642,"remaining_time":0.09488370566},
{"learn":[3.356880529],"iteration":790,"passed_time":0.3573203107,"remaining_time":0.09441206691},
{"learn":[3.353843509],"iteration":791,"passed_time":0.357698947,"remaining_time":0.09394113759},
{"learn":[3.353640253],"iteration":792,"passed_time":0.3580637852,"remaining_time":0.09346683926},
{"learn":[3.353055088],"iteration":793,"passed_time":0.3584426506,"remaining_time":0.09299645595},
{"learn":[3.351415617],"iteration":794,"passed_time":0.3588280875,"remaining_time":0.09252799742},
{"learn":[3.349169061],"iteration":795,"passed_time":0.359201577,"remaining_time":0.09205668557},
{"learn":[3.346211014],"iteration":796,"passed_time":0.3595748818,"remaining_time":0.09158557216},
{"learn":[3.344560452],"iteration":797,"passed_time":0.359943891,"remaining_time":0.09111361653},
{"learn":[3.344445461],"iteration":798,"passed_time":0.3603021878,"remaining_time":0.09063922371},
{"learn":[3.342608898],"iteration":799,"passed_time":0.3606793092,"remaining_time":0.0901698273},
{"learn":[3.339572899],"iteration":800,"passed_time":0.3610541539,"remaining_time":0.08970009567},
{"learn":[3.339309302],"iteration":801,"passed_time":0.3614147209,"remaining_time":0.08922707573},
{"learn":[3.33698088],"iteration":802,"passed_time":0.3618084748,"remaining_time":0.08876247763},
{"learn":[3.334746342],"iteration":803,"passed_time":0.362179417,"remaining_time":0.0882924947},
{"learn":[3.332048511],"iteration":804,"passed_time":0.3630216334,"remaining_time":0.08793691741},
{"learn":[3.331932544],"iteration":805,"passed_time":0.3634455903,"remaining_time":0.08747945969},
{"learn":[3.330541133],"iteration":806,"passed_time":0.3637988161,"remaining_time":0.08700516915},
{"learn":[3.329124989],"iteration":807,"passed_time":0.3641573884,"remaining_time":0.08653244874},
{"learn":[3.32583918],"iteration":808,"passed_time":0.3645252128,"remaining_time":0.08606219486},
{"learn":[3.325287299],"iteration":809,"passed_time":0.3648887852,"remaining_time":0.08559119653},
{"learn":[3.322745162],"iteration":810,"passed_time":0.3652732113,"remaining_time":0.08512532297},
{"learn":[3.319733662],"iteration":811,"passed_time":0.3656324466,"remaining_time":0.08465381768},
{"learn":[3.318080007],"iteration":812,"passed_time":0.3660161782,"remaining_time":0.08418822303},
{"learn":[3.317179538],"iteration":813,"passed_time":0.3663092501,"remaining_time":0.08370211365},
{"learn":[3.315685949],"iteration":814,"passed_time":0.3667333788,"remaining_time":0.08324622708},
{"learn":[3.314944576],"iteration":815,"passed_time":0.3670259595,"remaining_time":0.08276075558},
{"learn":[3.312369052],"iteration":816,"passed_time":0.3674763242,"remaining_time":0.08231109832},
{"learn":[3.312321621],"iteration":817,"passed_time":0.3676866897,"remaining_time":0.08180804097},
{"learn":[3.309465776],"iteration":818,"passed_time":0.3680871898,"remaining_time":0.08134771838},
{"learn":[3.308307377],"iteration":819,"passed_time":0.3683765539,"remaining_time":0.08086314597},
{"learn":[3.308076804],"iteration":820,"passed_time":0.3688144578,"remaining_time":0.08041143476},
{"learn":[3.305643326],"iteration":821,"passed_time":0.3691101056,"remaining_time":0.0799289523},
{"learn":[3.304154814],"iteration":822,"passed_time":0.369484442,"remaining_time":0.07946384719},
{"learn":[3.303076321],"iteration":823,"passed_time":0.3697710018,"remaining_time":0.07898021398},
{"learn":[3.301746372],"iteration":824,"passed_time":0.370202302,"remaining_time":0.07852776103},
{"learn":[3.301345455],"iteration":825,"passed_time":0.3704901282,"remaining_time":0.07804513597},
{"learn":[3.299181039],"iteration":826,"passed_time":0.3708807628,"remaining_time":0.07758448848},
{"learn":[3.297989357],"iteration":827,"passed_time":0.3712009127,"remaining_time":0.07710936833},
{"learn":[3.294775182],"iteration":828,"passed_time":0.3716461191,"remaining_time":0.0766604178},
{"learn":[3.293840636],"iteration":829,"passed_time":0.3719440886,"remaining_time":0.07618131936},
{"learn":[3.289279397],"iteration":830,"passed_time":0.3723552325,"remaining_time":0.07572567303},
{"learn":[3.286204979],"iteration":831,"passed_time":0.3726536087,"remaining_time":0.0752473633},
{"learn":[3.284833593],"iteration":832,"passed_time":0.373108022,"remaining_time":0.07480076791},
{"learn":[3.283519914],"iteration":833,"passed_time":0.3734099707,"remaining_time":0.07432380712},
{"learn":[3.282853026],"iteration":834,"passed_time":0.3738266802,"remaining_time":0.07386994279},
{"learn":[3.281944673],"iteration":835,"passed_time":0.374116723,"remaining_time":0.07339131886},
{"learn":[3.279764865],"iteration":836,"passed_time":0.3745483389,"remaining_time":0.07294071593},
{"learn":[3.277468839],"iteration":837,"passed_time":0.3748390869,"remaining_time":0.0724629261},
{"learn":[3.277124974],"iteration":838,"passed_time":0.3756949252,"remaining_time":0.07209402022},
{"learn":[3.275636037],"iteration":839,"passed_time":0.3760110794,"remaining_time":0.07162115799},
{"learn":[3.274413635],"iteration":840,"passed_time":0.3763627087,"remaining_time":0.07115537537},
{"learn":[3.272636087],"iteration":841,"passed_time":0.3772801257,"remaining_time":0.07079603309},
{"learn":[3.269644466],"iteration":842,"passed_time":0.3776827006,"remaining_time":0.07033948279},
{"learn":[3.26852083],"iteration":843,"passed_time":0.3780723286,"remaining_time":0.06988066737},
{"learn":[3.267820927],"iteration":844,"passed_time":0.3784712336,"remaining_time":0.06942371741},
{"learn":[3.267331099],"iteration":845,"passed_time":0.3788655138,"remaining_time":0.06896606279},
{"learn":[3.267231014],"iteration":846,"passed_time":0.3792400822,"remaining_time":0.06850499713},
{"learn":[3.267158695],"iteration":847,"passed_time":0.3795624943,"remaining_time":0.06803478672},
{"learn":[3.264718705],"iteration":848,"passed_time":0.3800397128,"remaining_time":0.06759245776},
{"learn":[3.261678512],"iteration":849,"passed_time":0.3803354229,"remaining_time":0.06711801581},
{"learn":[3.261368381],"iteration":850,"passed_time":0.3807581169,"remaining_time":0.06666622728},
{"learn":[3.260128799],"iteration":851,"passed_time":0.3810458816,"remaining_time":0.06619106863},
{"learn":[3.258972952],"iteration":852,"passed_time":0.3814646773,"remaining_time":0.06573893032},
{"learn":[3.258724846],"iteration":853,"passed_time":0.381754491,"remaining_time":0.06526481931},
{"learn":[3.25686724],"iteration":854,"passed_time":0.3821589803,"remaining_time":0.0648105873},
{"learn":[3.255750259],"iteration":855,"passed_time":0.3824505659,"remaining_time":0.06433747838},
{"learn":[3.254915866],"iteration":856,"passed_time":0.3828765947,"remaining_time":0.06388722642},
{"learn":[3.254348625],"iteration":857,"passed_time":0.3831758386,"remaining_time":0.06341604788},
{"learn":[3.253408514],"iteration":858,"passed_time":0.3835915251,"remaining_time":0.06296438304},
{"learn":[3.253291714],"iteration":859,"passed_time":0.3838695431,"remaining_time":0.06249039073},
{"learn":[3.250186342],"iteration":860,"passed_time":0.3843177865,"remaining_time":0.06204433486},
{"learn":[3.249141318],"iteration":861,"passed_time":0.3846052576,"remaining_time":0.06157253544},
{"learn":[3.246300388],"iteration":862,"passed_time":0.3849945642,"remaining_time":0.06111732942},
{"learn":[3.245205135],"iteration":863,"passed_time":0.3852849864,"remaining_time":0.06064671082},
{"learn":[3.244403535],"iteration":864,"passed_time":0.3857280923,"remaining_time":0.0602003381},
{"learn":[3.244211781],"iteration":865,"passed_time":0.3860120632,"remaining_time":0.05972934928},
{"learn":[3.242286347],"iteration":866,"passed_time":0.3863813824,"remaining_time":0.0592718845},
{"learn":[3.239606746],"iteration":867,"passed_time":0.3866701043,"remaining_time":0.0588023661},
{"learn":[3.236773361],"iteration":868,"passed_time":0.3870631273,"remaining_time":0.05834898697},
{"learn":[3.234552446],"iteration":869,"passed_time":0.3874553405,"remaining_time":0.05789562559},
{"learn":[3.233724647],"iteration":870,"passed_time":0.38774458,"remaining_time":0.05742715364},
{"learn":[3.230851485],"iteration":871,"passed_time":0.3881815432,"remaining_time":0.05698077699},
{"learn":[3.227728941],"iteration":872,"passed_time":0.3884785563,"remaining_time":0.0565140626},
{"learn":[3.225787575],"iteration":873,"passed_time":0.3888495866,"remaining_time":0.05605840722},
{"learn":[3.222797487],"iteration":874,"passed_time":0.3891472762,"remaining_time":0.05559246803},
{"learn":[3.22137014],"iteration":875,"passed_time":0.3895811516,"remaining_time":0.05514619041},
{"learn":[3.219701963],"iteration":876,"passed_time":0.3898731202,"remaining_time":0.05468003853},
{"learn":[3.21783327],"iteration":877,"passed_time":0.3902609813,"remaining_time":0.05422760788},
{"learn":[3.217713355],"iteration":878,"passed_time":0.3913542974,"remaining_time":0.05387243457},
{"learn":[3.217666091],"iteration":879,"passed_time":0.3917754106,"remaining_time":0.05342391963},
{"learn":[3.214962005],"iteration":880,"passed_time":0.3922179044,"remaining_time":0.05297835485},
{"learn":[3.214081828],"iteration":881,"passed_time":0.3936789342,"remaining_time":0.05266906376},
{"learn":[3.213358337],"iteration":882,"passed_time":0.3942048428,"remaining_time":0.05223325777},
{"learn":[3.210850401],"iteration":883,"passed_time":0.3945091899,"remaining_time":0.05176817424},
{"learn":[3.207810328],"iteration":884,"passed_time":0.3948062144,"remaining_time":0.05130250244},
{"learn":[3.204935073],"iteration":885,"passed_time":0.3950971335,"remaining_time":0.05083642576},
{"learn":[3.20280198],"iteration":886,"passed_time":0.3953918556,"remaining_time":0.05037122851},
{"learn":[3.200663495],"iteration":887,"passed_time":0.3956908103,"remaining_time":0.04990694905},
{"learn":[3.197301669],"iteration":888,"passed_time":0.3959806168,"remaining_time":0.04944189929},
{"learn":[3.195666943],"iteration":889,"passed_time":0.3962671516,"remaining_time":0.04897683896},
{"learn":[3.193886506],"iteration":890,"passed_time":0.3965573848,"remaining_time":0.04851263181},
{"learn":[3.190601248],"iteration":891,"passed_time":0.3968426172,"remaining_time":0.04804820926},
{"learn":[3.188983797],"iteration":892,"passed_time":0.3971377245,"remaining_time":0.04758537125},
{"learn":[3.187365749],"iteration":893,"passed_time":0.3974262424,"remaining_time":0.04712212717},
{"learn":[3.186160771],"iteration":894,"passed_time":0.3977273506,"remaining_time":0.04666075062},
{"learn":[3.185358981],"iteration":895,"passed_time":0.3980155863,"remaining_time":0.0461982377},
{"learn":[3.183832164],"iteration":896,"passed_time":0.3983086704,"remaining_time":0.04573667007},
{"learn":[3.183106966],"iteration":897,"passed_time":0.3985987182,"remaining_time":0.0452751328},
{"learn":[3.182838152],"iteration":898,"passed_time":0.3988806731,"remaining_time":0.04481306784},
{"learn":[3.180835453],"iteration":899,"passed_time":0.3991706235,"remaining_time":0.0443522915},
{"learn":[3.179957348],"iteration":900,"passed_time":0.3994581176,"remaining_time":0.04389162447},
{"learn":[3.179752966],"iteration":901,"passed_time":0.3997429985,"remaining_time":0.04343105749},
{"learn":[3.178851983],"iteration":902,"passed_time":0.4000356767,"remaining_time":0.04297171721},
{"learn":[3.176748586],"iteration":903,"passed_time":0.4003197801,"remaining_time":0.04251183505},
{"learn":[3.172960988],"iteration":904,"passed_time":0.4006188959,"remaining_time":0.04205391724},
{"learn":[3.172794225],"iteration":905,"passed_time":0.4009015467,"remaining_time":0.04159464171},
{"learn":[3.169996507],"iteration":906,"passed_time":0.4011917563,"remaining_time":0.04113653069},
{"learn":[3.16813015],"iteration":907,"passed_time":0.4033838628,"remaining_time":0.04087149271},
{"learn":[3.166920871],"iteration":908,"passed_time":0.4065293813,"remaining_time":0.04069766083},
{"learn":[3.16531606],"iteration":909,"passed_time":0.4070065117,"remaining_time":0.04025339127},
{"learn":[3.162035247],"iteration":910,"passed_time":0.4077975792,"remaining_time":0.03983971959},
{"learn":[3.16189467],"iteration":911,"passed_time":0.4080881976,"remaining_time":0.03937693134},
{"learn":[3.161008416],"iteration":912,"passed_time":0.408407426,"remaining_time":0.03891724651},
{"learn":[3.160560787],"iteration":913,"passed_time":0.4086907311,"remaining_time":0.03845448892},
{"learn":[3.160416261],"iteration":914,"passed_time":0.4089919245,"remaining_time":0.03799378534},
{"learn":[3.15844291],"iteration":915,"passed_time":0.4092862092,"remaining_time":0.03753279648},
{"learn":[3.155040501],"iteration":916,"passed_time":0.4095778514,"remaining_time":0.03707193202},
{"learn":[3.154937548],"iteration":917,"passed_time":0.4098629485,"remaining_time":0.03661085161},
{"learn":[3.153721161],"iteration":918,"passed_time":0.410145774,"remaining_time":0.03614995397},
{"learn":[3.153170511],"iteration":919,"passed_time":0.4104284026,"remaining_time":0.03568942631},
{"learn":[3.153113601],"iteration":920,"passed_time":0.4107099187,"remaining_time":0.03522918955},
{"learn":[3.150607379],"iteration":921,"passed_time":0.411523123,"remaining_time":0.0348143206},
{"learn":[3.148408359],"iteration":922,"passed_time":0.413509624,"remaining_time":0.03449646918},
{"learn":[3.147495728],"iteration":923,"passed_time":0.4141466719,"remaining_time":0.03406401197},
{"learn":[3.146946235],"iteration":924,"passed_time":0.4150649946,"remaining_time":0.03365391848},
{"learn":[3.14472738],"iteration":925,"passed_time":0.4159725346,"remaining_time":0.03324186561},
{"learn":[3.144469477],"iteration":926,"passed_time":0.4168939064,"remaining_time":0.03282983297},
{"learn":[3.142975516],"iteration":927,"passed_time":0.4178685949,"remaining_time":0.03242083926},
{"learn":[3.14079113],"iteration":928,"passed_time":0.418747056,"remaining_time":0.03200327339},
{"learn":[3.138173032],"iteration":929,"passed_time":0.4196215043,"remaining_time":0.0315844143},
{"learn":[3.136352813],"iteration":930,"passed_time":0.420423272,"remaining_time":0.03115918987},
{"learn":[3.133735004],"iteration":931,"passed_time":0.4213170418,"remaining_time":0.03073987},
{"learn":[3.1319496],"iteration":932,"passed_time":0.4221591623,"remaining_time":0.03031582409},
{"learn":[3.129865343],"iteration":933,"passed_time":0.4229962175,"remaining_time":0.029890525},
{"learn":[3.129830206],"iteration":934,"passed_time":0.4237108565,"remaining_time":0.02945583494},
{"learn":[3.126676562],"iteration":935,"passed_time":0.4243754977,"remaining_time":0.02901712805},
{"learn":[3.12645665],"iteration":936,"passed_time":0.4253038871,"remaining_time":0.02859567224},
{"learn":[3.126378007],"iteration":937,"passed_time":0.4262160864,"remaining_time":0.02817206541},
{"learn":[3.124621914],"iteration":938,"passed_time":0.4271266999,"remaining_time":0.0277473149},
{"learn":[3.123379018],"iteration":939,"passed_time":0.4279913635,"remaining_time":0.02731859767},
{"learn":[3.123332451],"iteration":940,"passed_time":0.4288231867,"remaining_time":0.02688689481},
{"learn":[3.122432444],"iteration":941,"passed_time":0.4296405933,"remaining_time":0.02645345479},
{"learn":[3.121889006],"iteration":942,"passed_time":0.4306084741,"remaining_time":0.02602829589},
{"learn":[3.121070914],"iteration":943,"passed_time":0.4315846224,"remaining_time":0.0256024776},
{"learn":[3.118444705],"iteration":944,"passed_time":0.4324811378,"remaining_time":0.02517085987},
{"learn":[3.116820458],"iteration":945,"passed_time":0.4333568125,"remaining_time":0.02473706963},
{"learn":[3.114971041],"iteration":946,"passed_time":0.4341706923,"remaining_time":0.02429888774},
{"learn":[3.114685138],"iteration":947,"passed_time":0.4351133623,"remaining_time":0.02386697768},
{"learn":[3.113399363],"iteration":948,"passed_time":0.4360316542,"remaining_time":0.0234326811},
{"learn":[3.110575399],"iteration":949,"passed_time":0.4369443346,"remaining_time":0.02299707024},
{"learn":[3.110466553],"iteration":950,"passed_time":0.4377977281,"remaining_time":0.02255740134},
{"learn":[3.108691641],"iteration":951,"passed_time":0.4386610322,"remaining_time":0.02211736297},
{"learn":[3.107898017],"iteration":952,"passed_time":0.4394593928,"remaining_time":0.02167323343},
{"learn":[3.105551729],"iteration":953,"passed_time":0.4403618017,"remaining_time":0.02123337828},
{"learn":[3.104824945],"iteration":954,"passed_time":0.4411619178,"remaining_time":0.02078773435},
{"learn":[3.103186704],"iteration":955,"passed_time":0.441501392,"remaining_time":0.02032014775},
{"learn":[3.102330655],"iteration":956,"passed_time":0.4418374126,"remaining_time":0.01985267371},
{"learn":[3.102291298],"iteration":957,"passed_time":0.4421781934,"remaining_time":0.0193856828},
{"learn":[3.100363529],"iteration":958,"passed_time":0.4425203237,"remaining_time":0.0189190128},
{"learn":[3.097871596],"iteration":959,"passed_time":0.4428586717,"remaining_time":0.01845244466},
{"learn":[3.097372213],"iteration":960,"passed_time":0.4431965315,"remaining_time":0.01798612355},
{"learn":[3.095981813],"iteration":961,"passed_time":0.4435370524,"remaining_time":0.01752017463},
{"learn":[3.095347452],"iteration":962,"passed_time":0.4438739342,"remaining_time":0.01705434638},
{"learn":[3.094728409],"iteration":963,"passed_time":0.4442343809,"remaining_time":0.01658966568},
{"learn":[3.094118537],"iteration":964,"passed_time":0.4445782252,"remaining_time":0.01612459884},
{"learn":[3.093793695],"iteration":965,"passed_time":0.4449215353,"remaining_time":0.01565976418},
{"learn":[3.092581602],"iteration":966,"passed_time":0.4452799158,"remaining_time":0.01519569516},
{"learn":[3.091694202],"iteration":967,"passed_time":0.4456706478,"remaining_time":0.01473291398},
{"learn":[3.090298312],"iteration":968,"passed_time":0.4460809082,"remaining_time":0.01427090625},
{"learn":[3.090020107],"iteration":969,"passed_time":0.4464445279,"remaining_time":0.01380756272},
{"learn":[3.088949869],"iteration":970,"passed_time":0.4468269228,"remaining_time":0.01334498534},
{"learn":[3.086700204],"iteration":971,"passed_time":0.4473012182,"remaining_time":0.01288522028},
{"learn":[3.086584317],"iteration":972,"passed_time":0.4476418121,"remaining_time":0.01242171524},
{"learn":[3.084850742],"iteration":973,"passed_time":0.4479913681,"remaining_time":0.01195870182},
{"learn":[3.084239948],"iteration":974,"passed_time":0.4483294161,"remaining_time":0.01149562605},
{"learn":[3.082561673],"iteration":975,"passed_time":0.4486695039,"remaining_time":0.01103285665},
{"learn":[3.07991814],"iteration":976,"passed_time":0.4490071138,"remaining_time":0.01057028006},
{"learn":[3.079350277],"iteration":977,"passed_time":0.4493749339,"remaining_time":0.01010863859},
{"learn":[3.077637462],"iteration":978,"passed_time":0.4497262274,"remaining_time":0.009646834295},
{"learn":[3.076733301],"iteration":979,"passed_time":0.4500689734,"remaining_time":0.00918508109},
{"learn":[3.07594065],"iteration":980,"passed_time":0.4504306507,"remaining_time":0.00872393717},
{"learn":[3.072594655],"iteration":981,"passed_time":0.450811258,"remaining_time":0.008263342815},
{"learn":[3.071977674],"iteration":982,"passed_time":0.4512294223,"remaining_time":0.007803560711},
{"learn":[3.069532634],"iteration":983,"passed_time":0.4515779466,"remaining_time":0.007342730839},
{"learn":[3.068870784],"iteration":984,"passed_time":0.4519383224,"remaining_time":0.006882309478},
{"learn":[3.068801463],"iteration":985,"passed_time":0.4523019285,"remaining_time":0.006422136915},
{"learn":[3.067433249],"iteration":986,"passed_time":0.4526792468,"remaining_time":0.005962340636},
{"learn":[3.065611456],"iteration":987,"passed_time":0.4530578494,"remaining_time":0.005502726916},
{"learn":[3.063039162],"iteration":988,"passed_time":0.453425812,"remaining_time":0.005043158677},
{"learn":[3.06177873],"iteration":989,"passed_time":0.4538004827,"remaining_time":0.00458384326},
{"learn":[3.061689148],"iteration":990,"passed_time":0.4541608084,"remaining_time":0.004124568391},
{"learn":[3.058984039],"iteration":991,"passed_time":0.4545294289,"remaining_time":0.00366555991},
{"learn":[3.057492984],"iteration":992,"passed_time":0.4549200291,"remaining_time":0.003206888423},
{"learn":[3.057290731],"iteration":993,"passed_time":0.4552920424,"remaining_time":0.002748241704},
{"learn":[3.056068348],"iteration":994,"passed_time":0.4556996739,"remaining_time":0.00228994811},
{"learn":[3.054987307],"iteration":995,"passed_time":0.4560430227,"remaining_time":0.001831498083},
{"learn":[3.054200234],"iteration":996,"passed_time":0.4563984285,"remaining_time":0.001373315231},
{"learn":[3.052732869],"iteration":997,"passed_time":0.456778279,"remaining_time":0.0009153873328},
{"learn":[3.051787862],"iteration":998,"passed_time":0.457137354,"remaining_time":0.0004575949489},
{"learn":[3.051366222],"iteration":999,"passed_time":0.457498145,"remaining_time":0}
]}